{
  "links": "https://www.ycombinator.com/companies/finch",
  "name": "Finch",
  "headline": "Finch is the universal API for payroll and HR",
  "batch": "S20",
  "description": "Finch is the API to access payroll and HR systems. We allow admins to connect their company in a compliant and secure manner to applications. Finch integrates across providers enabling developers to access a previously closed system and are at the source of truth for employee data and money flow. Our API powers use cases across lending, insurance, benefits, FP&A, and HR applications.",
  "activity_status": "Active",
  "website": "https://tryfinch.com",
  "founded_date": 2020.0,
  "team_size": 63.0,
  "location": "San Francisco",
  "group_partner": "Dalton Caldwell",
  "group_partner_yc": "https://www.ycombinator.com/people/dalton-caldwell",
  "company_linkedin": null,
  "company_twitter": null,
  "tags": "industry:fintech; industry:hr-tech; industry:api; location:san-francisco-bay-area",
  "founders": [
    {
      "name": "Jeremy Zhang, Founder",
      "description": "CEO/Co-founder of Finch",
      "linkedin": "https://www.linkedin.com/in/jeremyziyuzhang/"
    },
    {
      "name": "Ansel Parikh, Founder",
      "description": null,
      "linkedin": "https://www.linkedin.com/in/ansel-parikh/"
    }
  ],
  "status": true,
  "markdown": "raw_markdown=\"[Announcing Expanded Platform Features for Recordkeepers and TPAs | Read more --> ](https://tryfinch.com/<https:/www.tryfinch.com/blog/announcing-expanded-platform-features-for-recordkeepers-and-tpas>)[](https://tryfinch.com/<#>)\\n[![](https://cdn.prod.website-files.com/63dd790039a2b29044f7d608/63dd95e9ebe31f280b24f322_logo.svg)](https://tryfinch.com/</>)\\n  * Products\\nThe Unified API for HRIS and Payroll\\n[Explore our API![](https://cdn.prod.website-files.com/63dd790039a2b29044f7d608/63def4266af00bf50447512f_text-arrow.svg)](https://tryfinch.com/</finch-api>)\\nProducts\\n[![](https://cdn.prod.website-files.com/63dd790039a2b29044f7d608/657cb9766bf7002bcf801e30_nav-organization.svg)Organization ->Company and employee data](https://tryfinch.com/</product/organization>)\\n[![](https://cdn.prod.website-files.com/63dd790039a2b29044f7d608/657cb976e9032dd1c8ba8d1c_nav-payroll.svg)Payroll ->Payroll and tax information](https://tryfinch.com/</product/payroll>)\\n[![](https://cdn.prod.website-files.com/63dd790039a2b29044f7d608/657cb976d4c0352fd6d895b1_nav-deductions.svg)Deductions ->Deductions and contributions](https://tryfinch.com/</product/deductions>)\\n  * Solutions\\nSolutions\\nEmployment infrastructure built for your use case\\n    * [![](https://cdn.prod.website-files.com/63dd790039a2b29044f7d608/6619c520d848e7067c81276c_401k-menu-icon.svg)401k and Retirement ->](https://tryfinch.com/</solutions/401k-retirement>)\\n    * [![](https://cdn.prod.website-files.com/63dd790039a2b29044f7d608/657cd35ae263ba3262a0a055_solutions-benefits.svg)Employee Benefits ->](https://tryfinch.com/</solutions/employee-benefits>)\\n    * [![](https://cdn.prod.website-files.com/63dd790039a2b29044f7d608/657cd3598331325e706358b1_solutions-b2b.svg)B2B Fintech ->](https://tryfinch.com/</solutions/b2b-fintech>)\\n    * [![](https://cdn.prod.website-files.com/63dd790039a2b29044f7d608/657cd35ae263ba3262a0a05a_solutions-insurance.svg)Insurance ->](https://tryfinch.com/</solutions/insurance>)\\n    * [![](https://cdn.prod.website-files.com/63dd790039a2b29044f7d608/657cd35a79dce6447e540791_solutions-hr.svg)HR Technology ->](https://tryfinch.com/</solutions/hr-technology>)\\n    * [![](https://cdn.prod.website-files.com/63dd790039a2b29044f7d608/657cd35be4daac8653498ff6_solutions-tax.svg)Tax and Compliance ->](https://tryfinch.com/</solutions/tax-compliance>)\\nCustomer Stories\\n[See all![](https://cdn.prod.website-files.com/63dd790039a2b29044f7d608/63def4266af00bf50447512f_text-arrow.svg)](https://tryfinch.com/</tag/case-study>)\\n[![](https://cdn.prod.website-files.com/63deb4700c95fc8b0d114fde/67a242c49b3c20afc29f62e5_Ubiquity%20\\\\(1\\\\).png)Ubiquity Saves 80 Hours per Week with Finch-Powered AutomationRead More![](https://cdn.prod.website-files.com/63dd790039a2b29044f7d608/63def4266af00bf50447512f_text-arrow.svg)](https://tryfinch.com/</blog/ubiquity-saves-80-hours-per-week-with-automation>)\\n[![](https://cdn.prod.website-files.com/63deb4700c95fc8b0d114fde/6710395b3bef7018ccfa2416_Awardco%20%2B%20UKG%20\\\\(1\\\\).png)Awardco and UKG Launch Partnership 10 Months Faster with FinchRead More![](https://cdn.prod.website-files.com/63dd790039a2b29044f7d608/63def4266af00bf50447512f_text-arrow.svg)](https://tryfinch.com/</blog/awardco-and-ukg-launch-partnership-10-months-faster-with-finch>)\\n  * Integrations\\nIntegrations\\nGrow with the industry's largest Provider Network\\n[![](https://cdn.prod.website-files.com/63deb4700c95fc8b0d114fde/6584a02009a769f1934bc1a4_quickbooks.svg)QuickBooks Online Payroll](https://tryfinch.com/</integrations/quickbooks-online-payroll>)\\n[![](https://cdn.prod.website-files.com/63deb4700c95fc8b0d114fde/657cc7024a96bde1dff43629_gusto.svg)Gusto](https://tryfinch.com/</integrations/gusto>)\\n[![](https://cdn.prod.website-files.com/63deb4700c95fc8b0d114fde/665f4b6908b3ce2be8217e54_Rippling-Tiny-Logo.svg)Rippling](https://tryfinch.com/</integrations/rippling>)\\n[![](https://cdn.prod.website-files.com/63deb4700c95fc8b0d114fde/657cc71b6fed63da3ebfd366_paychex-flex.svg)Paychex](https://tryfinch.com/</integrations/paychex>)\\n[![](https://cdn.prod.website-files.com/63deb4700c95fc8b0d114fde/657cc7281cbe7e9f27ee96c2_insperity.svg)Insperity](https://tryfinch.com/</integrations/insperity>)\\n[![](https://cdn.prod.website-files.com/63deb4700c95fc8b0d114fde/65849f24aeebf6b33527f493_paycom.svg)Paycom](https://tryfinch.com/</integrations/paycom>)\\n[![](https://cdn.prod.website-files.com/63deb4700c95fc8b0d114fde/65849f0ec020ed1a1129db58_Paylocity.svg)Paylocity](https://tryfinch.com/</integrations/paylocity>)\\n[![](https://cdn.prod.website-files.com/63deb4700c95fc8b0d114fde/657cc74c8b15ebef1f10efcd_paycor.svg)Paycor](https://tryfinch.com/</integrations/paycor>)\\n[![](https://cdn.prod.website-files.com/63deb4700c95fc8b0d114fde/657cc7597fb127b254d81496_ukg-pro.svg)UKG Pro](https://tryfinch.com/</integrations/ultipro-ukg-pro>)\\n[![](https://cdn.prod.website-files.com/63deb4700c95fc8b0d114fde/666b28edcf0fdd0a9cefac36_trinet.svg)TriNet (fka Zenefits)](https://tryfinch.com/</integrations/trinet>)\\n[![](https://cdn.prod.website-files.com/63deb4700c95fc8b0d114fde/657cc76f912f38ebb160d04c_justworks.svg)Justworks](https://tryfinch.com/</integrations/justworks>)\\n[All Integrations![](https://cdn.prod.website-files.com/63dd790039a2b29044f7d608/63def4266af00bf50447512f_text-arrow.svg)](https://tryfinch.com/</integrations>)\\n  * Learn\\nDevelopers\\n    * [![](https://cdn.prod.website-files.com/63dd790039a2b29044f7d608/657cdff8bbc17a556dea0d80_resources-docs.svg)Docs](https://tryfinch.com/<https:/developer.tryfinch.com/>)\\n    * [![](https://cdn.prod.website-files.com/63dd790039a2b29044f7d608/657cdff85bf5a83f4f5acaf3_resources-status.svg)API Status](https://tryfinch.com/<https:/status.tryfinch.com/>)\\n    * [![](https://cdn.prod.website-files.com/63dd790039a2b29044f7d608/657cdff80ebdd1f979c554c2_resources-changelog.svg)Changelog](https://tryfinch.com/<https:/changelog.tryfinch.com/>)\\nSupport\\n    * [![](https://cdn.prod.website-files.com/63dd790039a2b29044f7d608/664f91f95e897f99aa646fd7_icon-support.svg)Help Center](https://tryfinch.com/<https:/support.tryfinch.com/hc/en-us>)\\nAbout Finch\\n    * [![](https://cdn.prod.website-files.com/63dd790039a2b29044f7d608/657cdff9dd1607d8158c4ff1_resources-about.svg)Company](https://tryfinch.com/</company/about>)\\n    * [![](https://cdn.prod.website-files.com/63dd790039a2b29044f7d608/657cdff8e0747baa9bf63b93_resources-careers.svg)Careers](https://tryfinch.com/</careers>)\\n    * [![](https://cdn.prod.website-files.com/63dd790039a2b29044f7d608/65dcf0b83dac61f48eeb7584_for-partners-nav-icon.svg)For Partners](https://tryfinch.com/</for-partners>)\\n    * [![](https://cdn.prod.website-files.com/63dd790039a2b29044f7d608/657cdff83970773550b88b4d_resources-security.svg)Security](https://tryfinch.com/</company/security>)\\n    * [![](https://cdn.prod.website-files.com/63dd790039a2b29044f7d608/657cdff867546782a3db2846_resources-privacy.svg)Privacy](https://tryfinch.com/<https:/www.tryfinch.com/legal/privacy>)\\nResources\\n    * [![](https://cdn.prod.website-files.com/63dd790039a2b29044f7d608/657cdff814d9bd3327b13952_resources-blog.svg)Blog](https://tryfinch.com/</blog>)\\n    * [![](https://cdn.prod.website-files.com/63dd790039a2b29044f7d608/657cdffa3e44cc316890cbe4_resources-whitepapers.svg)Whitepapers](https://tryfinch.com/</whitepapers>)\\n    * [![](https://cdn.prod.website-files.com/63dd790039a2b29044f7d608/664f92611bbc9020ad5e002d_icon-customer-stories.svg)Customer Stories](https://tryfinch.com/</tag/case-study>)\\nFrom the blog\\n[See all posts![](https://cdn.prod.website-files.com/63dd790039a2b29044f7d608/63def4266af00bf50447512f_text-arrow.svg)](https://tryfinch.com/</blog>)\\n[![](https://cdn.prod.website-files.com/63deb4700c95fc8b0d114fde/6751d9c7cb9992623918650d_Blog%2C%20Documents%20Beta%20v2.png)Introducing Documents (Beta) – Expanding our Unified API Platform to Employee DocumentsRead More![](https://cdn.prod.website-files.com/63dd790039a2b29044f7d608/63def4266af00bf50447512f_text-arrow.svg)](https://tryfinch.com/</blog/introducing-documents-beta---expanding-our-unified-api-platform-to-employee-documents>)\\n[![](https://cdn.prod.website-files.com/63deb4700c95fc8b0d114fde/6733e00076f9b18e5e18be78_Cover%20\\\\(1\\\\).png)Announcing Expanded Platform Features for Recordkeepers and TPAsRead More![](https://cdn.prod.website-files.com/63dd790039a2b29044f7d608/63def4266af00bf50447512f_text-arrow.svg)](https://tryfinch.com/</blog/announcing-expanded-platform-features-for-recordkeepers-and-tpas>)\\n  * [Pricing](https://tryfinch.com/</pricing>)\\n  * [Sign In](https://tryfinch.com/<https:/dashboard.tryfinch.com/login>)\\n\\n\\n[Sign Up](https://tryfinch.com/<https:/dashboard.tryfinch.com/signup>)[Talk to Sales](https://tryfinch.com/</sales>)\\n[Sign In](https://tryfinch.com/<https:/dashboard.tryfinch.com/login>)[Sign Up](https://tryfinch.com/<https:/dashboard.tryfinch.com/signup>)[Talk to Sales](https://tryfinch.com/</sales>)[](https://tryfinch.com/<#>)\\n# The #1 API for Employment Systems\\nUnlock organization, pay, and benefits data from the industry's largest HRIS and payroll provider network.\\n[Talk to Sales](https://tryfinch.com/</sales>)[Sign Up![](https://cdn.prod.website-files.com/63dd790039a2b29044f7d608/63e063443700f08aebd8c221_black-arrow.svg)](https://tryfinch.com/<https:/dashboard.tryfinch.com/signup>)\\n![](https://cdn.prod.website-files.com/63dd790039a2b29044f7d608/63e063c247ab583d56b7d185_hero-image.webp)\\n## Powering integrations for hundreds of platforms\\n![](https://cdn.prod.website-files.com/63deb4700c95fc8b0d114fde/64824b95e6213b74fbafb18b_corporate-merch.svg)\\n![](https://cdn.prod.website-files.com/63deb4700c95fc8b0d114fde/64824bf269a0fcdd714ba474_sequoia.svg)\\n![](https://cdn.prod.website-files.com/63deb4700c95fc8b0d114fde/65858ef1a455fcc487f3d29c_tempopay-logo.svg)\\n![](https://cdn.prod.website-files.com/63deb4700c95fc8b0d114fde/648b602d1281398f2b299c12_carta-logo-new.svg)\\n![](https://cdn.prod.website-files.com/63deb4700c95fc8b0d114fde/648b618d7ccab58cb7134389_human-interest-logo.svg)\\n![](https://cdn.prod.website-files.com/63deb4700c95fc8b0d114fde/64824b820a94f4a9faff4e2e_betterment.svg)\\n![](https://cdn.prod.website-files.com/63deb4700c95fc8b0d114fde/675c85c3b006101abcd58897_ameritas-logo.svg)\\n![](https://cdn.prod.website-files.com/63deb4700c95fc8b0d114fde/675c938bffc314a9c2c6b452_bill_com-logo.svg)\\n![](https://cdn.prod.website-files.com/63deb4700c95fc8b0d114fde/675c85e272a21c325cf19ade_inspira-logo.svg)\\n![](https://cdn.prod.website-files.com/63deb4700c95fc8b0d114fde/64824bbf8e314e41e34c823b_mainstreet.svg)\\n![](https://cdn.prod.website-files.com/63deb4700c95fc8b0d114fde/64824c041219f477b42121b6_trainual.svg)\\n![](https://cdn.prod.website-files.com/63deb4700c95fc8b0d114fde/64824bdc23bfed0f6e365cac_perk-up.svg)\\n![](https://cdn.prod.website-files.com/63deb4700c95fc8b0d114fde/64824b95e6213b74fbafb18b_corporate-merch.svg)\\n![](https://cdn.prod.website-files.com/63deb4700c95fc8b0d114fde/64824bf269a0fcdd714ba474_sequoia.svg)\\n![](https://cdn.prod.website-files.com/63deb4700c95fc8b0d114fde/65858ef1a455fcc487f3d29c_tempopay-logo.svg)\\n![](https://cdn.prod.website-files.com/63deb4700c95fc8b0d114fde/648b602d1281398f2b299c12_carta-logo-new.svg)\\n![](https://cdn.prod.website-files.com/63deb4700c95fc8b0d114fde/648b618d7ccab58cb7134389_human-interest-logo.svg)\\n![](https://cdn.prod.website-files.com/63deb4700c95fc8b0d114fde/64824b820a94f4a9faff4e2e_betterment.svg)\\n![](https://cdn.prod.website-files.com/63deb4700c95fc8b0d114fde/675c85c3b006101abcd58897_ameritas-logo.svg)\\n![](https://cdn.prod.website-files.com/63deb4700c95fc8b0d114fde/675c938bffc314a9c2c6b452_bill_com-logo.svg)\\n![](https://cdn.prod.website-files.com/63deb4700c95fc8b0d114fde/675c85e272a21c325cf19ade_inspira-logo.svg)\\n![](https://cdn.prod.website-files.com/63deb4700c95fc8b0d114fde/64824bbf8e314e41e34c823b_mainstreet.svg)\\n![](https://cdn.prod.website-files.com/63deb4700c95fc8b0d114fde/64824c041219f477b42121b6_trainual.svg)\\n![](https://cdn.prod.website-files.com/63deb4700c95fc8b0d114fde/64824bdc23bfed0f6e365cac_perk-up.svg)\\n![](https://cdn.prod.website-files.com/63dd790039a2b29044f7d608/653159ec06e3cc2e454180c4_app-left.webp)\\n![](https://cdn.prod.website-files.com/63dd790039a2b29044f7d608/653159ed76e6a269bc215b39_app-right.webp)\\nBuilt for innovators\\n## Accelerate your integrations roadmap\\nFinch powers integrations for innovators across Employee Benefits, HR Tech, B2B Fintech, and more.\\n[Sign Up](https://tryfinch.com/<https:/dashboard.tryfinch.com/signup>)\\n[![](https://cdn.prod.website-files.com/63dd790039a2b29044f7d608/657cb810b376a8df459ab4ef_nav-deductions.svg)HR Tech ->Streamline customer onboarding and trigger automations for when employees join, leave, get promoted, and more.Empower employees with training like![Trainual](https://cdn.prod.website-files.com/63dd790039a2b29044f7d608/63e0201368f8e94d41786a12_trainual.svg)](https://tryfinch.com/</solutions/hr-technology>)\\n[![](https://cdn.prod.website-files.com/63dd790039a2b29044f7d608/65a1d0628fb71aacd6614481_solution-401k-retirement.svg)401k and Retirement ->Connect to sponsor payroll systems to simplify onboarding, enroll employees, modify deferral rates, and run audits.Make retirement savings grow like![Human Interest](https://cdn.prod.website-files.com/63dd790039a2b29044f7d608/63e546d7c8989b2c7f7f0423_Frame.svg)](https://tryfinch.com/</solutions/401k-retirement>)\\n[![](https://cdn.prod.website-files.com/63dd790039a2b29044f7d608/65a1d0624621b6acf81a188e_solutions-employee-benefits.svg)Employee Benefits ->Enroll employees into benefits and make updates to payroll deductions and contributions automatically.Automate payroll deductions like![TempoPay](https://cdn.prod.website-files.com/63dd790039a2b29044f7d608/65a1d18873331a788fc5f34f_tempopay.svg)](https://tryfinch.com/</solutions/employee-benefits>)\\n[![](https://cdn.prod.website-files.com/63dd790039a2b29044f7d608/657cb81217e73f3ab2e38c95_nav-payroll.svg)B2B Fintech ->Power financial insights and analytics to help employers with headcount planning, salary benchmarking, and more.Power salary insights like![Carta](https://cdn.prod.website-files.com/63dd790039a2b29044f7d608/64dd6c709b0c6c5764667c2e_logo-carta.png)](https://tryfinch.com/</solutions/b2b-fintech>)\\n[![](https://cdn.prod.website-files.com/63dd790039a2b29044f7d608/65a1d0628fb71aacd661448d_solutions-tax-compliance.svg)Tax and Compliance ->Help companies provision new employees, manage certification processes, and determine tax credit eligibility.Power compliance automation like![SecureFrame](https://cdn.prod.website-files.com/63dd790039a2b29044f7d608/65a1d188f5eef2ee37c95a90_secureframe%20logo.svg)](https://tryfinch.com/</solutions/tax-compliance>)\\n[![](https://cdn.prod.website-files.com/63dd790039a2b29044f7d608/65a1d0627c2bc43447bdaea8_solutions-insurance.svg)Insurance ->Leverage payroll integrations to streamline audits, reduce premium leakage, and avoid surprise bills for your clients.Optimize premiums like![InsurePay](https://cdn.prod.website-files.com/63dd790039a2b29044f7d608/65a1d18889f7470b14fcf546_insurepay%20logo.svg)](https://tryfinch.com/</solutions/insurance>)\\nDeveloper-first\\n## Why developers love building with Finch\\n![](https://cdn.prod.website-files.com/63dd790039a2b29044f7d608/65a1d0620d444dfb5d624014_market-coverage.svg)\\n### Market-leading coverage\\nConnect to any HRIS or payroll system in Finch's provider network through our unified data model. As we add new systems, turn them on with one click.\\n![](https://cdn.prod.website-files.com/63dd790039a2b29044f7d608/65a1d0621b211a9d01e37546_enterprise-security.svg)\\n### Enterprise-grade security\\nFinch utilizes best-in-class encryption protocols like TLS 1.2 and AES 256 bit encryption to keep your data safe in transit and at rest.\\n![](https://cdn.prod.website-files.com/63dd790039a2b29044f7d608/65a1d062ad502dd94aac0f01_dev-read-write.svg)\\n### Read and write functionality\\nRead and sync your customers' organization, pay, and benefits data. Write deductions and contributions back to the system of record.\\n![](https://cdn.prod.website-files.com/63dd790039a2b29044f7d608/65a1d06273331a788fc56f44_dev-experience.svg)\\n### Best in class developer experience\\nFinch streamlines integration build and maintenance, so you can focus on your core product. Get up and running quickly with our sandbox and SDKs.\\nHow it works\\n## Onboard customers seamlessly with Finch Connect\\n[Try the demo now![](https://cdn.prod.website-files.com/63dd790039a2b29044f7d608/63def4266af00bf50447512f_text-arrow.svg)](https://tryfinch.com/<https:/demo.tryfinch.com/>)\\n### [Prioritize privacyFinch discloses data privacy practices right from the start, so end users know where and how their data is transferred.](https://tryfinch.com/<#>)### [Confirm permissionsFinch Connect displays the granular permissions needed to access the requested data. We only share data that's been approved.](https://tryfinch.com/<#>)### [Select a providerOnce your user approves, they select their employment system from Finch’s network of providers.](https://tryfinch.com/<#>)### [Authenticate accessYour user is prompted to log in to their account, granting your application access to their employment data.](https://tryfinch.com/<#>)\\n![](https://cdn.prod.website-files.com/63dd790039a2b29044f7d608/63e7f098aed3c62ac736c25a_how-slide1.svg)\\n![](https://cdn.prod.website-files.com/63dd790039a2b29044f7d608/63e7f09a60afc2db629781ff_how-slide2.svg)\\n![](https://cdn.prod.website-files.com/63dd790039a2b29044f7d608/63e7f09beaf85342b74c1c80_how-slide3.svg)\\n![](https://cdn.prod.website-files.com/63dd790039a2b29044f7d608/63e7f09c63db55b3a40e6336_how-slide4.svg)\\n[](https://tryfinch.com/<#>)[](https://tryfinch.com/<#>)\\n### Security at Finch\\nFinch is committed to preserving trust in the employment ecosystem. That’s why we protect the data of our customers, employers, and employees every step of the way.\\n[Read more about Security![](https://cdn.prod.website-files.com/63dd790039a2b29044f7d608/63def4266af00bf50447512f_text-arrow.svg)](https://tryfinch.com/</company/security>)\\n![](https://cdn.prod.website-files.com/63dd790039a2b29044f7d608/63debc17dd106676fa1f72b4_soc2.png)![](https://cdn.prod.website-files.com/63dd790039a2b29044f7d608/63debc171693d10ca8f1dcb0_ccpa.png)\\nUnified API\\n## One API to unite every provider\\nFinch standardizes employment data across every provider. So you don't have to.\\n[HRIS](https://tryfinch.com/<#w-tabs-0-data-w-pane-0>)\\n  * [Company](https://tryfinch.com/<#>)\\n![](https://cdn.prod.website-files.com/63dd790039a2b29044f7d608/65984787579506910d578ad2_Company%2C%20Desktop.svg)![](https://cdn.prod.website-files.com/63dd790039a2b29044f7d608/65984788910b2a186e6ee5ac_Company%2C%20Mobile.svg)\\nRead basic company data including legal name, EIN, bank accounts, entity type, and locations.\\n[Read the company API](https://tryfinch.com/<https:/developer.tryfinch.com/docs/reference/b3A6MTcxMzYwODg-company>)\\n  * [Directory](https://tryfinch.com/<#>)\\n![](https://cdn.prod.website-files.com/63dd790039a2b29044f7d608/65984787f52776c8e4b48907_Directory%2C%20Desktop.svg)![](https://cdn.prod.website-files.com/63dd790039a2b29044f7d608/65984788eddfa6c533ef3861_Directory%2C%20Mobile.svg)\\nRead company directory and organization structure including the names of individuals and the reporting structure.[](https://tryfinch.com/<https:/developer.tryfinch.com/docs/reference/b3A6MTcxMzYwODk-directory>)\\n[Read the directory API](https://tryfinch.com/<https:/developer.tryfinch.com/docs/reference/b3A6MTcxMzYwODk-directory>)\\n  * [Individual](https://tryfinch.com/<#>)\\n![](https://cdn.prod.website-files.com/63dd790039a2b29044f7d608/659847889c70b88d4420f078_Individual%2C%20Desktop.svg)![](https://cdn.prod.website-files.com/63dd790039a2b29044f7d608/65984788a6bfc64b03e422bf_Individual%2C%20Mobile.svg)\\nRead individual data including name, email, phone number, date of birth, and residence.[](https://tryfinch.com/<https:/developer.tryfinch.com/docs/reference/b3A6MTcxMzYwODk-directory>)\\n[Read the individual API](https://tryfinch.com/<https:/developer.tryfinch.com/docs/reference/b3A6MTcxMzYwOTA-individual>)\\n  * [Employment](https://tryfinch.com/<#>)\\n![](https://cdn.prod.website-files.com/63dd790039a2b29044f7d608/659847896dbe9e3e0f24d1c2_Employment%2C%20Desktop.svg)![](https://cdn.prod.website-files.com/63dd790039a2b29044f7d608/65984788b005318c21d8f53b_Employment%2C%20Mobile.svg)\\nRead employment data including income, employment type, start date, end date, and location.[](https://tryfinch.com/<https:/developer.tryfinch.com/docs/reference/b3A6MTcxMzYwODk-directory>)\\n[Read the employment API](https://tryfinch.com/<https:/developer.tryfinch.com/docs/reference/b3A6MTcxMzYwOTE-employment>)\\n  * [Payment](https://tryfinch.com/<#>)\\n![](https://cdn.prod.website-files.com/63dd790039a2b29044f7d608/65984789ea4932a3f476db3e_Payment%2C%20Desktop.svg)![](https://cdn.prod.website-files.com/63dd790039a2b29044f7d608/659847896dbe9e3e0f24d1d3_Payment%2C%20Mobile.svg)\\nRead all payments made the company including pay date, pay periods, and gross and net pay.[](https://tryfinch.com/<https:/developer.tryfinch.com/docs/reference/b3A6MTcxMzYwODk-directory>)\\n[Read the payment API](https://tryfinch.com/<https:/developer.tryfinch.com/docs/reference/b3A6MTcxMzYwOTI-payment>)\\n  * [Pay Statement](https://tryfinch.com/<#>)\\n![](https://cdn.prod.website-files.com/63dd790039a2b29044f7d608/65984788234010c15e913e0f_Pay%20Statement%2C%20Desktop.svg)![](https://cdn.prod.website-files.com/63dd790039a2b29044f7d608/65984788234010c15e913e53_Pay%20Statement%2C%20Mobile.svg)\\nRead all data on a specific pay statement including earnings, deductions, and taxes.[](https://tryfinch.com/<https:/developer.tryfinch.com/docs/reference/b3A6MTcxMzYwODk-directory>)\\n[Read the pay statement API](https://tryfinch.com/<https:/developer.tryfinch.com/docs/reference/b3A6MTcxMzYwOTM-pay-statement>)\\n  * [Benefits](https://tryfinch.com/<#>)\\n![](https://cdn.prod.website-files.com/63dd790039a2b29044f7d608/659847871b5b40bcd3e7267e_Benefits%2C%20Desktop.svg)![](https://cdn.prod.website-files.com/63dd790039a2b29044f7d608/65984787963a78669f075d14_Benefits%2C%20Mobile.svg)\\nRead and write benefits information, including creating benefits and enrolling individuals.[](https://tryfinch.com/<https:/developer.tryfinch.com/docs/reference/b3A6MTcxMzYwODk-directory>)\\n[Read the benefits API](https://tryfinch.com/<https:/developer.tryfinch.com/docs/reference/d22e2304e8c9c-get-all-benefits>)\\n\\n\\nIntegrations\\n## Access the global employment ecosystem\\nGain instant compatibility with hundreds of employment systems. \\n[Explore integrations![](https://cdn.prod.website-files.com/63dd790039a2b29044f7d608/63def4266af00bf50447512f_text-arrow.svg)](https://tryfinch.com/</integrations>)\\n![](https://cdn.prod.website-files.com/63dd790039a2b29044f7d608/63e058ac03e95f4d830150da_integration-cards.svg)\\n## Customer Stories\\n### You’ll be in good company\\n[See all![](https://cdn.prod.website-files.com/63dd790039a2b29044f7d608/63def4266af00bf50447512f_text-arrow.svg)](https://tryfinch.com/</tag/case-study>)\\n![](https://cdn.prod.website-files.com/63deb4700c95fc8b0d114fde/67a242c49b3c20afc29f62e5_Ubiquity%20\\\\(1\\\\).png)\\nCase Study\\n### Ubiquity Saves 80 Hours per Week with Finch-Powered Automation\\n![](https://cdn.prod.website-files.com/63deb4700c95fc8b0d114fde/65bd4e2b193b4b8fbf0fb39c_Headshot.jpeg)\\nKiera Blessing\\nFebruary 4, 2025\\n[View author](https://tryfinch.com/</authors/kiera-blessing>)\\n[View blog post](https://tryfinch.com/</blog/ubiquity-saves-80-hours-per-week-with-automation>)\\n![](https://cdn.prod.website-files.com/63deb4700c95fc8b0d114fde/673e5959fe833a63700b696d_CandorIQ.png)\\nCase Study\\n### CandorIQ Saves $500K/year and Accelerates Innovation with Finch \\n![](https://cdn.prod.website-files.com/63deb4700c95fc8b0d114fde/65bd4e2b193b4b8fbf0fb39c_Headshot.jpeg)\\nKiera Blessing\\nNovember 21, 2024\\n[View author](https://tryfinch.com/</authors/kiera-blessing>)\\n[View blog post](https://tryfinch.com/</blog/candoriq-saves-500k-year-and-accelerates-innovation-with-finch>)\\n![](https://cdn.prod.website-files.com/63deb4700c95fc8b0d114fde/6710395b3bef7018ccfa2416_Awardco%20%2B%20UKG%20\\\\(1\\\\).png)\\nCase Study\\n### Awardco and UKG Launch Partnership 10 Months Faster with Finch\\n![](https://cdn.prod.website-files.com/63deb4700c95fc8b0d114fde/65bd4e2b193b4b8fbf0fb39c_Headshot.jpeg)\\nKiera Blessing\\nOctober 17, 2024\\n[View author](https://tryfinch.com/</authors/kiera-blessing>)\\n[View blog post](https://tryfinch.com/</blog/awardco-and-ukg-launch-partnership-10-months-faster-with-finch>)\\n### Start building with Finch\\nGet your API keys or contact us for more information.[](https://tryfinch.com/<https:/dashboard.tryfinch.com/signup>)\\n[Get API Keys](https://tryfinch.com/<https:/dashboard.tryfinch.com/signup>)[Contact Sales](https://tryfinch.com/</sales>)\\n  * Products\\n  * [Organization](https://tryfinch.com/</product/organization>)\\n  * [Payroll](https://tryfinch.com/</product/payroll>)\\n  * [Deductions](https://tryfinch.com/</product/deductions>)\\n\\n\\n  * Solutions\\n  * [401k and Retirement](https://tryfinch.com/</solutions/401k-retirement>)\\n  * [Employee Benefits](https://tryfinch.com/</solutions/employee-benefits>)\\n  * [HR Technology](https://tryfinch.com/</solutions/hr-technology>)\\n  * [B2B Fintech](https://tryfinch.com/</solutions/b2b-fintech>)\\n  * [Tax & Compliance](https://tryfinch.com/</solutions/tax-compliance>)\\n  * [Insurance](https://tryfinch.com/</solutions/insurance>)\\n\\n\\n  * Integrations\\n  * [Intuit Quickbooks](https://tryfinch.com/<https:/www.tryfinch.com/integrations/quickbooks-online-payroll>)\\n  * [Gusto](https://tryfinch.com/<https:/www.tryfinch.com/integrations/gusto>)\\n  * [Run Powered by ADP](https://tryfinch.com/<https:/www.tryfinch.com/integrations/adp-run>)\\n  * [Paychex Flex](https://tryfinch.com/<https:/www.tryfinch.com/integrations/paychex>)\\n  * [See all![](https://cdn.prod.website-files.com/63dd790039a2b29044f7d608/63e063443700f08aebd8c221_black-arrow.svg)](https://tryfinch.com/</integrations>)\\n\\n\\n  * Build with Finch\\n  * [Documentation](https://tryfinch.com/<https:/developer.tryfinch.com/>)\\n  * [Finch API](https://tryfinch.com/</finch-api>)\\n  * [API Status](https://tryfinch.com/<https:/status.tryfinch.com/>)\\n  * [Changelog](https://tryfinch.com/<https:/changelog.tryfinch.com/>)\\n\\n\\n  * Resources\\n  * [Blog](https://tryfinch.com/</blog>)\\n  * [Customer Stories](https://tryfinch.com/</tag/case-study>)\\n  * [Whitepapers](https://tryfinch.com/</whitepapers>)\\n\\n\\n  * Finch\\n  * [About Us](https://tryfinch.com/</company/about>)\\n  * [Careers](https://tryfinch.com/</careers>)\\n  * [For Employers](https://tryfinch.com/</for-employers>)\\n  * [For Partners](https://tryfinch.com/</for-partners>)\\n\\n\\nFollow Us\\n[![](https://cdn.prod.website-files.com/63dd790039a2b29044f7d608/63dd9929c48a7e4bb078baef_linkedin.svg)](https://tryfinch.com/<https:/www.linkedin.com/company/finchapi/>)\\n[Sign In](https://tryfinch.com/<https:/dashboard.tryfinch.com/login>)[Sign Up](https://tryfinch.com/<https:/dashboard.tryfinch.com/signup>)[Talk to Sales](https://tryfinch.com/</sales>)\\n[![](https://cdn.prod.website-files.com/63dd790039a2b29044f7d608/63dd95e9ebe31f280b24f322_logo.svg)](https://tryfinch.com/</>)\\n© 2025 Finch Inc.\\n[Privacy Policy](https://tryfinch.com/</legal/privacy>)[Terms](https://tryfinch.com/</legal/terms>)[Security](https://tryfinch.com/</company/security>)\\n\" markdown_with_citations=\"Announcing Expanded Platform Features for Recordkeepers and TPAs | Read more --> ⟨1⟩[](https://tryfinch.com/<#>)\\n![⟨2⟩](https://tryfinch.com/</>)\\n  * Products\\nThe Unified API for HRIS and Payroll\\nExplore our API![⟨3⟩](https://tryfinch.com/</finch-api>)\\nProducts\\n![⟨4⟩Organization ->Company and employee data](https://tryfinch.com/</product/organization>)\\n![⟨5⟩Payroll ->Payroll and tax information](https://tryfinch.com/</product/payroll>)\\n![⟨6⟩Deductions ->Deductions and contributions](https://tryfinch.com/</product/deductions>)\\n  * Solutions\\nSolutions\\nEmployment infrastructure built for your use case\\n    * ![⟨7⟩401k and Retirement ->](https://tryfinch.com/</solutions/401k-retirement>)\\n    * ![⟨8⟩Employee Benefits ->](https://tryfinch.com/</solutions/employee-benefits>)\\n    * ![⟨9⟩B2B Fintech ->](https://tryfinch.com/</solutions/b2b-fintech>)\\n    * ![⟨10⟩Insurance ->](https://tryfinch.com/</solutions/insurance>)\\n    * ![⟨11⟩HR Technology ->](https://tryfinch.com/</solutions/hr-technology>)\\n    * ![⟨12⟩Tax and Compliance ->](https://tryfinch.com/</solutions/tax-compliance>)\\nCustomer Stories\\nSee all![⟨3⟩](https://tryfinch.com/</tag/case-study>)\\n![⟨13⟩.png)Ubiquity Saves 80 Hours per Week with Finch-Powered AutomationRead More![](https://cdn.prod.website-files.com/63dd790039a2b29044f7d608/63def4266af00bf50447512f_text-arrow.svg)](https://tryfinch.com/</blog/ubiquity-saves-80-hours-per-week-with-automation>)\\n![⟨14⟩.png)Awardco and UKG Launch Partnership 10 Months Faster with FinchRead More![](https://cdn.prod.website-files.com/63dd790039a2b29044f7d608/63def4266af00bf50447512f_text-arrow.svg)](https://tryfinch.com/</blog/awardco-and-ukg-launch-partnership-10-months-faster-with-finch>)\\n  * Integrations\\nIntegrations\\nGrow with the industry's largest Provider Network\\n![⟨15⟩QuickBooks Online Payroll](https://tryfinch.com/</integrations/quickbooks-online-payroll>)\\n![⟨16⟩Gusto](https://tryfinch.com/</integrations/gusto>)\\n![⟨17⟩Rippling](https://tryfinch.com/</integrations/rippling>)\\n![⟨18⟩Paychex](https://tryfinch.com/</integrations/paychex>)\\n![⟨19⟩Insperity](https://tryfinch.com/</integrations/insperity>)\\n![⟨20⟩Paycom](https://tryfinch.com/</integrations/paycom>)\\n![⟨21⟩Paylocity](https://tryfinch.com/</integrations/paylocity>)\\n![⟨22⟩Paycor](https://tryfinch.com/</integrations/paycor>)\\n![⟨23⟩UKG Pro](https://tryfinch.com/</integrations/ultipro-ukg-pro>)\\n![⟨24⟩TriNet (fka Zenefits)](https://tryfinch.com/</integrations/trinet>)\\n![⟨25⟩Justworks](https://tryfinch.com/</integrations/justworks>)\\nAll Integrations![⟨3⟩](https://tryfinch.com/</integrations>)\\n  * Learn\\nDevelopers\\n    * ![⟨26⟩Docs](https://tryfinch.com/<https:/developer.tryfinch.com/>)\\n    * ![⟨27⟩API Status](https://tryfinch.com/<https:/status.tryfinch.com/>)\\n    * ![⟨28⟩Changelog](https://tryfinch.com/<https:/changelog.tryfinch.com/>)\\nSupport\\n    * ![⟨29⟩Help Center](https://tryfinch.com/<https:/support.tryfinch.com/hc/en-us>)\\nAbout Finch\\n    * ![⟨30⟩Company](https://tryfinch.com/</company/about>)\\n    * ![⟨31⟩Careers](https://tryfinch.com/</careers>)\\n    * ![⟨32⟩For Partners](https://tryfinch.com/</for-partners>)\\n    * ![⟨33⟩Security](https://tryfinch.com/</company/security>)\\n    * ![⟨34⟩Privacy](https://tryfinch.com/<https:/www.tryfinch.com/legal/privacy>)\\nResources\\n    * ![⟨35⟩Blog](https://tryfinch.com/</blog>)\\n    * ![⟨36⟩Whitepapers](https://tryfinch.com/</whitepapers>)\\n    * ![⟨37⟩Customer Stories](https://tryfinch.com/</tag/case-study>)\\nFrom the blog\\nSee all posts![⟨3⟩](https://tryfinch.com/</blog>)\\n![⟨38⟩Introducing Documents (Beta) – Expanding our Unified API Platform to Employee DocumentsRead More![](https://cdn.prod.website-files.com/63dd790039a2b29044f7d608/63def4266af00bf50447512f_text-arrow.svg)](https://tryfinch.com/</blog/introducing-documents-beta---expanding-our-unified-api-platform-to-employee-documents>)\\n![⟨39⟩.png)Announcing Expanded Platform Features for Recordkeepers and TPAsRead More![](https://cdn.prod.website-files.com/63dd790039a2b29044f7d608/63def4266af00bf50447512f_text-arrow.svg)](https://tryfinch.com/</blog/announcing-expanded-platform-features-for-recordkeepers-and-tpas>)\\n  * Pricing⟨40⟩\\n  * Sign In⟨41⟩\\n\\n\\nSign Up⟨42⟩Talk to Sales⟨43⟩\\nSign In⟨41⟩Sign Up⟨42⟩Talk to Sales⟨43⟩[](https://tryfinch.com/<#>)\\n# The #1 API for Employment Systems\\nUnlock organization, pay, and benefits data from the industry's largest HRIS and payroll provider network.\\nTalk to Sales⟨43⟩Sign Up![⟨44⟩](https://tryfinch.com/<https:/dashboard.tryfinch.com/signup>)\\n![](https://cdn.prod.website-files.com/63dd790039a2b29044f7d608/63e063c247ab583d56b7d185_hero-image.webp)\\n## Powering integrations for hundreds of platforms\\n![](https://cdn.prod.website-files.com/63deb4700c95fc8b0d114fde/64824b95e6213b74fbafb18b_corporate-merch.svg)\\n![](https://cdn.prod.website-files.com/63deb4700c95fc8b0d114fde/64824bf269a0fcdd714ba474_sequoia.svg)\\n![](https://cdn.prod.website-files.com/63deb4700c95fc8b0d114fde/65858ef1a455fcc487f3d29c_tempopay-logo.svg)\\n![](https://cdn.prod.website-files.com/63deb4700c95fc8b0d114fde/648b602d1281398f2b299c12_carta-logo-new.svg)\\n![](https://cdn.prod.website-files.com/63deb4700c95fc8b0d114fde/648b618d7ccab58cb7134389_human-interest-logo.svg)\\n![](https://cdn.prod.website-files.com/63deb4700c95fc8b0d114fde/64824b820a94f4a9faff4e2e_betterment.svg)\\n![](https://cdn.prod.website-files.com/63deb4700c95fc8b0d114fde/675c85c3b006101abcd58897_ameritas-logo.svg)\\n![](https://cdn.prod.website-files.com/63deb4700c95fc8b0d114fde/675c938bffc314a9c2c6b452_bill_com-logo.svg)\\n![](https://cdn.prod.website-files.com/63deb4700c95fc8b0d114fde/675c85e272a21c325cf19ade_inspira-logo.svg)\\n![](https://cdn.prod.website-files.com/63deb4700c95fc8b0d114fde/64824bbf8e314e41e34c823b_mainstreet.svg)\\n![](https://cdn.prod.website-files.com/63deb4700c95fc8b0d114fde/64824c041219f477b42121b6_trainual.svg)\\n![](https://cdn.prod.website-files.com/63deb4700c95fc8b0d114fde/64824bdc23bfed0f6e365cac_perk-up.svg)\\n![](https://cdn.prod.website-files.com/63deb4700c95fc8b0d114fde/64824b95e6213b74fbafb18b_corporate-merch.svg)\\n![](https://cdn.prod.website-files.com/63deb4700c95fc8b0d114fde/64824bf269a0fcdd714ba474_sequoia.svg)\\n![](https://cdn.prod.website-files.com/63deb4700c95fc8b0d114fde/65858ef1a455fcc487f3d29c_tempopay-logo.svg)\\n![](https://cdn.prod.website-files.com/63deb4700c95fc8b0d114fde/648b602d1281398f2b299c12_carta-logo-new.svg)\\n![](https://cdn.prod.website-files.com/63deb4700c95fc8b0d114fde/648b618d7ccab58cb7134389_human-interest-logo.svg)\\n![](https://cdn.prod.website-files.com/63deb4700c95fc8b0d114fde/64824b820a94f4a9faff4e2e_betterment.svg)\\n![](https://cdn.prod.website-files.com/63deb4700c95fc8b0d114fde/675c85c3b006101abcd58897_ameritas-logo.svg)\\n![](https://cdn.prod.website-files.com/63deb4700c95fc8b0d114fde/675c938bffc314a9c2c6b452_bill_com-logo.svg)\\n![](https://cdn.prod.website-files.com/63deb4700c95fc8b0d114fde/675c85e272a21c325cf19ade_inspira-logo.svg)\\n![](https://cdn.prod.website-files.com/63deb4700c95fc8b0d114fde/64824bbf8e314e41e34c823b_mainstreet.svg)\\n![](https://cdn.prod.website-files.com/63deb4700c95fc8b0d114fde/64824c041219f477b42121b6_trainual.svg)\\n![](https://cdn.prod.website-files.com/63deb4700c95fc8b0d114fde/64824bdc23bfed0f6e365cac_perk-up.svg)\\n![](https://cdn.prod.website-files.com/63dd790039a2b29044f7d608/653159ec06e3cc2e454180c4_app-left.webp)\\n![](https://cdn.prod.website-files.com/63dd790039a2b29044f7d608/653159ed76e6a269bc215b39_app-right.webp)\\nBuilt for innovators\\n## Accelerate your integrations roadmap\\nFinch powers integrations for innovators across Employee Benefits, HR Tech, B2B Fintech, and more.\\nSign Up⟨42⟩\\n![⟨45⟩HR Tech ->Streamline customer onboarding and trigger automations for when employees join, leave, get promoted, and more.Empower employees with training like![Trainual⟨46⟩]](https://tryfinch.com/</solutions/hr-technology>)\\n![⟨47⟩401k and Retirement ->Connect to sponsor payroll systems to simplify onboarding, enroll employees, modify deferral rates, and run audits.Make retirement savings grow like![Human Interest⟨48⟩]](https://tryfinch.com/</solutions/401k-retirement>)\\n![⟨49⟩Employee Benefits ->Enroll employees into benefits and make updates to payroll deductions and contributions automatically.Automate payroll deductions like![TempoPay⟨50⟩]](https://tryfinch.com/</solutions/employee-benefits>)\\n![⟨51⟩B2B Fintech ->Power financial insights and analytics to help employers with headcount planning, salary benchmarking, and more.Power salary insights like![Carta⟨52⟩]](https://tryfinch.com/</solutions/b2b-fintech>)\\n![⟨53⟩Tax and Compliance ->Help companies provision new employees, manage certification processes, and determine tax credit eligibility.Power compliance automation like![SecureFrame⟨54⟩]](https://tryfinch.com/</solutions/tax-compliance>)\\n![⟨55⟩Insurance ->Leverage payroll integrations to streamline audits, reduce premium leakage, and avoid surprise bills for your clients.Optimize premiums like![InsurePay⟨56⟩]](https://tryfinch.com/</solutions/insurance>)\\nDeveloper-first\\n## Why developers love building with Finch\\n![](https://cdn.prod.website-files.com/63dd790039a2b29044f7d608/65a1d0620d444dfb5d624014_market-coverage.svg)\\n### Market-leading coverage\\nConnect to any HRIS or payroll system in Finch's provider network through our unified data model. As we add new systems, turn them on with one click.\\n![](https://cdn.prod.website-files.com/63dd790039a2b29044f7d608/65a1d0621b211a9d01e37546_enterprise-security.svg)\\n### Enterprise-grade security\\nFinch utilizes best-in-class encryption protocols like TLS 1.2 and AES 256 bit encryption to keep your data safe in transit and at rest.\\n![](https://cdn.prod.website-files.com/63dd790039a2b29044f7d608/65a1d062ad502dd94aac0f01_dev-read-write.svg)\\n### Read and write functionality\\nRead and sync your customers' organization, pay, and benefits data. Write deductions and contributions back to the system of record.\\n![](https://cdn.prod.website-files.com/63dd790039a2b29044f7d608/65a1d06273331a788fc56f44_dev-experience.svg)\\n### Best in class developer experience\\nFinch streamlines integration build and maintenance, so you can focus on your core product. Get up and running quickly with our sandbox and SDKs.\\nHow it works\\n## Onboard customers seamlessly with Finch Connect\\nTry the demo now![⟨3⟩](https://tryfinch.com/<https:/demo.tryfinch.com/>)\\n### Prioritize privacyFinch discloses data privacy practices right from the start, so end users know where and how their data is transferred.⟨57⟩### Confirm permissionsFinch Connect displays the granular permissions needed to access the requested data. We only share data that's been approved.⟨57⟩### Select a providerOnce your user approves, they select their employment system from Finch’s network of providers.⟨57⟩### Authenticate accessYour user is prompted to log in to their account, granting your application access to their employment data.⟨57⟩\\n![](https://cdn.prod.website-files.com/63dd790039a2b29044f7d608/63e7f098aed3c62ac736c25a_how-slide1.svg)\\n![](https://cdn.prod.website-files.com/63dd790039a2b29044f7d608/63e7f09a60afc2db629781ff_how-slide2.svg)\\n![](https://cdn.prod.website-files.com/63dd790039a2b29044f7d608/63e7f09beaf85342b74c1c80_how-slide3.svg)\\n![](https://cdn.prod.website-files.com/63dd790039a2b29044f7d608/63e7f09c63db55b3a40e6336_how-slide4.svg)\\n[](https://tryfinch.com/<#>)[](https://tryfinch.com/<#>)\\n### Security at Finch\\nFinch is committed to preserving trust in the employment ecosystem. That’s why we protect the data of our customers, employers, and employees every step of the way.\\nRead more about Security![⟨3⟩](https://tryfinch.com/</company/security>)\\n![](https://cdn.prod.website-files.com/63dd790039a2b29044f7d608/63debc17dd106676fa1f72b4_soc2.png)![](https://cdn.prod.website-files.com/63dd790039a2b29044f7d608/63debc171693d10ca8f1dcb0_ccpa.png)\\nUnified API\\n## One API to unite every provider\\nFinch standardizes employment data across every provider. So you don't have to.\\nHRIS⟨58⟩\\n  * Company⟨57⟩\\n![](https://cdn.prod.website-files.com/63dd790039a2b29044f7d608/65984787579506910d578ad2_Company%2C%20Desktop.svg)![](https://cdn.prod.website-files.com/63dd790039a2b29044f7d608/65984788910b2a186e6ee5ac_Company%2C%20Mobile.svg)\\nRead basic company data including legal name, EIN, bank accounts, entity type, and locations.\\nRead the company API⟨59⟩\\n  * Directory⟨57⟩\\n![](https://cdn.prod.website-files.com/63dd790039a2b29044f7d608/65984787f52776c8e4b48907_Directory%2C%20Desktop.svg)![](https://cdn.prod.website-files.com/63dd790039a2b29044f7d608/65984788eddfa6c533ef3861_Directory%2C%20Mobile.svg)\\nRead company directory and organization structure including the names of individuals and the reporting structure.[](https://tryfinch.com/<https:/developer.tryfinch.com/docs/reference/b3A6MTcxMzYwODk-directory>)\\nRead the directory API⟨60⟩\\n  * Individual⟨57⟩\\n![](https://cdn.prod.website-files.com/63dd790039a2b29044f7d608/659847889c70b88d4420f078_Individual%2C%20Desktop.svg)![](https://cdn.prod.website-files.com/63dd790039a2b29044f7d608/65984788a6bfc64b03e422bf_Individual%2C%20Mobile.svg)\\nRead individual data including name, email, phone number, date of birth, and residence.[](https://tryfinch.com/<https:/developer.tryfinch.com/docs/reference/b3A6MTcxMzYwODk-directory>)\\nRead the individual API⟨61⟩\\n  * Employment⟨57⟩\\n![](https://cdn.prod.website-files.com/63dd790039a2b29044f7d608/659847896dbe9e3e0f24d1c2_Employment%2C%20Desktop.svg)![](https://cdn.prod.website-files.com/63dd790039a2b29044f7d608/65984788b005318c21d8f53b_Employment%2C%20Mobile.svg)\\nRead employment data including income, employment type, start date, end date, and location.[](https://tryfinch.com/<https:/developer.tryfinch.com/docs/reference/b3A6MTcxMzYwODk-directory>)\\nRead the employment API⟨62⟩\\n  * Payment⟨57⟩\\n![](https://cdn.prod.website-files.com/63dd790039a2b29044f7d608/65984789ea4932a3f476db3e_Payment%2C%20Desktop.svg)![](https://cdn.prod.website-files.com/63dd790039a2b29044f7d608/659847896dbe9e3e0f24d1d3_Payment%2C%20Mobile.svg)\\nRead all payments made the company including pay date, pay periods, and gross and net pay.[](https://tryfinch.com/<https:/developer.tryfinch.com/docs/reference/b3A6MTcxMzYwODk-directory>)\\nRead the payment API⟨63⟩\\n  * Pay Statement⟨57⟩\\n![](https://cdn.prod.website-files.com/63dd790039a2b29044f7d608/65984788234010c15e913e0f_Pay%20Statement%2C%20Desktop.svg)![](https://cdn.prod.website-files.com/63dd790039a2b29044f7d608/65984788234010c15e913e53_Pay%20Statement%2C%20Mobile.svg)\\nRead all data on a specific pay statement including earnings, deductions, and taxes.[](https://tryfinch.com/<https:/developer.tryfinch.com/docs/reference/b3A6MTcxMzYwODk-directory>)\\nRead the pay statement API⟨64⟩\\n  * Benefits⟨57⟩\\n![](https://cdn.prod.website-files.com/63dd790039a2b29044f7d608/659847871b5b40bcd3e7267e_Benefits%2C%20Desktop.svg)![](https://cdn.prod.website-files.com/63dd790039a2b29044f7d608/65984787963a78669f075d14_Benefits%2C%20Mobile.svg)\\nRead and write benefits information, including creating benefits and enrolling individuals.[](https://tryfinch.com/<https:/developer.tryfinch.com/docs/reference/b3A6MTcxMzYwODk-directory>)\\nRead the benefits API⟨65⟩\\n\\n\\nIntegrations\\n## Access the global employment ecosystem\\nGain instant compatibility with hundreds of employment systems. \\nExplore integrations![⟨3⟩](https://tryfinch.com/</integrations>)\\n![](https://cdn.prod.website-files.com/63dd790039a2b29044f7d608/63e058ac03e95f4d830150da_integration-cards.svg)\\n## Customer Stories\\n### You’ll be in good company\\nSee all![⟨3⟩](https://tryfinch.com/</tag/case-study>)\\n![](https://cdn.prod.website-files.com/63deb4700c95fc8b0d114fde/67a242c49b3c20afc29f62e5_Ubiquity%20\\\\(1\\\\).png)\\nCase Study\\n### Ubiquity Saves 80 Hours per Week with Finch-Powered Automation\\n![](https://cdn.prod.website-files.com/63deb4700c95fc8b0d114fde/65bd4e2b193b4b8fbf0fb39c_Headshot.jpeg)\\nKiera Blessing\\nFebruary 4, 2025\\nView author⟨66⟩\\nView blog post⟨67⟩\\n![](https://cdn.prod.website-files.com/63deb4700c95fc8b0d114fde/673e5959fe833a63700b696d_CandorIQ.png)\\nCase Study\\n### CandorIQ Saves $500K/year and Accelerates Innovation with Finch \\n![](https://cdn.prod.website-files.com/63deb4700c95fc8b0d114fde/65bd4e2b193b4b8fbf0fb39c_Headshot.jpeg)\\nKiera Blessing\\nNovember 21, 2024\\nView author⟨66⟩\\nView blog post⟨68⟩\\n![](https://cdn.prod.website-files.com/63deb4700c95fc8b0d114fde/6710395b3bef7018ccfa2416_Awardco%20%2B%20UKG%20\\\\(1\\\\).png)\\nCase Study\\n### Awardco and UKG Launch Partnership 10 Months Faster with Finch\\n![](https://cdn.prod.website-files.com/63deb4700c95fc8b0d114fde/65bd4e2b193b4b8fbf0fb39c_Headshot.jpeg)\\nKiera Blessing\\nOctober 17, 2024\\nView author⟨66⟩\\nView blog post⟨69⟩\\n### Start building with Finch\\nGet your API keys or contact us for more information.[](https://tryfinch.com/<https:/dashboard.tryfinch.com/signup>)\\nGet API Keys⟨42⟩Contact Sales⟨43⟩\\n  * Products\\n  * Organization⟨70⟩\\n  * Payroll⟨71⟩\\n  * Deductions⟨72⟩\\n\\n\\n  * Solutions\\n  * 401k and Retirement⟨73⟩\\n  * Employee Benefits⟨74⟩\\n  * HR Technology⟨75⟩\\n  * B2B Fintech⟨76⟩\\n  * Tax & Compliance⟨77⟩\\n  * Insurance⟨78⟩\\n\\n\\n  * Integrations\\n  * Intuit Quickbooks⟨79⟩\\n  * Gusto⟨80⟩\\n  * Run Powered by ADP⟨81⟩\\n  * Paychex Flex⟨82⟩\\n  * See all![⟨44⟩](https://tryfinch.com/</integrations>)\\n\\n\\n  * Build with Finch\\n  * Documentation⟨83⟩\\n  * Finch API⟨84⟩\\n  * API Status⟨85⟩\\n  * Changelog⟨86⟩\\n\\n\\n  * Resources\\n  * Blog⟨87⟩\\n  * Customer Stories⟨88⟩\\n  * Whitepapers⟨89⟩\\n\\n\\n  * Finch\\n  * About Us⟨90⟩\\n  * Careers⟨91⟩\\n  * For Employers⟨92⟩\\n  * For Partners⟨93⟩\\n\\n\\nFollow Us\\n![⟨94⟩](https://tryfinch.com/<https:/www.linkedin.com/company/finchapi/>)\\nSign In⟨41⟩Sign Up⟨42⟩Talk to Sales⟨43⟩\\n![⟨2⟩](https://tryfinch.com/</>)\\n© 2025 Finch Inc.\\nPrivacy Policy⟨95⟩Terms⟨96⟩Security⟨97⟩\\n\" references_markdown='\\n\\n## References\\n\\n⟨1⟩ https://tryfinch.com/<https:/www.tryfinch.com/blog/announcing-expanded-platform-features-for-recordkeepers-and-tpas>: Announcing Expanded Platform Features for Recordkeepers and TPAs | Read more --> \\n⟨2⟩ https://cdn.prod.website-files.com/63dd790039a2b29044f7d608/63dd95e9ebe31f280b24f322_logo.svg: ![\\n⟨3⟩ https://cdn.prod.website-files.com/63dd790039a2b29044f7d608/63def4266af00bf50447512f_text-arrow.svg: Explore our API![\\n⟨4⟩ https://cdn.prod.website-files.com/63dd790039a2b29044f7d608/657cb9766bf7002bcf801e30_nav-organization.svg: ![\\n⟨5⟩ https://cdn.prod.website-files.com/63dd790039a2b29044f7d608/657cb976e9032dd1c8ba8d1c_nav-payroll.svg: ![\\n⟨6⟩ https://cdn.prod.website-files.com/63dd790039a2b29044f7d608/657cb976d4c0352fd6d895b1_nav-deductions.svg: ![\\n⟨7⟩ https://cdn.prod.website-files.com/63dd790039a2b29044f7d608/6619c520d848e7067c81276c_401k-menu-icon.svg: ![\\n⟨8⟩ https://cdn.prod.website-files.com/63dd790039a2b29044f7d608/657cd35ae263ba3262a0a055_solutions-benefits.svg: ![\\n⟨9⟩ https://cdn.prod.website-files.com/63dd790039a2b29044f7d608/657cd3598331325e706358b1_solutions-b2b.svg: ![\\n⟨10⟩ https://cdn.prod.website-files.com/63dd790039a2b29044f7d608/657cd35ae263ba3262a0a05a_solutions-insurance.svg: ![\\n⟨11⟩ https://cdn.prod.website-files.com/63dd790039a2b29044f7d608/657cd35a79dce6447e540791_solutions-hr.svg: ![\\n⟨12⟩ https://cdn.prod.website-files.com/63dd790039a2b29044f7d608/657cd35be4daac8653498ff6_solutions-tax.svg: ![\\n⟨13⟩ https://cdn.prod.website-files.com/63deb4700c95fc8b0d114fde/67a242c49b3c20afc29f62e5_Ubiquity%20\\\\(1\\\\: ![\\n⟨14⟩ https://cdn.prod.website-files.com/63deb4700c95fc8b0d114fde/6710395b3bef7018ccfa2416_Awardco%20%2B%20UKG%20\\\\(1\\\\: ![\\n⟨15⟩ https://cdn.prod.website-files.com/63deb4700c95fc8b0d114fde/6584a02009a769f1934bc1a4_quickbooks.svg: ![\\n⟨16⟩ https://cdn.prod.website-files.com/63deb4700c95fc8b0d114fde/657cc7024a96bde1dff43629_gusto.svg: ![\\n⟨17⟩ https://cdn.prod.website-files.com/63deb4700c95fc8b0d114fde/665f4b6908b3ce2be8217e54_Rippling-Tiny-Logo.svg: ![\\n⟨18⟩ https://cdn.prod.website-files.com/63deb4700c95fc8b0d114fde/657cc71b6fed63da3ebfd366_paychex-flex.svg: ![\\n⟨19⟩ https://cdn.prod.website-files.com/63deb4700c95fc8b0d114fde/657cc7281cbe7e9f27ee96c2_insperity.svg: ![\\n⟨20⟩ https://cdn.prod.website-files.com/63deb4700c95fc8b0d114fde/65849f24aeebf6b33527f493_paycom.svg: ![\\n⟨21⟩ https://cdn.prod.website-files.com/63deb4700c95fc8b0d114fde/65849f0ec020ed1a1129db58_Paylocity.svg: ![\\n⟨22⟩ https://cdn.prod.website-files.com/63deb4700c95fc8b0d114fde/657cc74c8b15ebef1f10efcd_paycor.svg: ![\\n⟨23⟩ https://cdn.prod.website-files.com/63deb4700c95fc8b0d114fde/657cc7597fb127b254d81496_ukg-pro.svg: ![\\n⟨24⟩ https://cdn.prod.website-files.com/63deb4700c95fc8b0d114fde/666b28edcf0fdd0a9cefac36_trinet.svg: ![\\n⟨25⟩ https://cdn.prod.website-files.com/63deb4700c95fc8b0d114fde/657cc76f912f38ebb160d04c_justworks.svg: ![\\n⟨26⟩ https://cdn.prod.website-files.com/63dd790039a2b29044f7d608/657cdff8bbc17a556dea0d80_resources-docs.svg: ![\\n⟨27⟩ https://cdn.prod.website-files.com/63dd790039a2b29044f7d608/657cdff85bf5a83f4f5acaf3_resources-status.svg: ![\\n⟨28⟩ https://cdn.prod.website-files.com/63dd790039a2b29044f7d608/657cdff80ebdd1f979c554c2_resources-changelog.svg: ![\\n⟨29⟩ https://cdn.prod.website-files.com/63dd790039a2b29044f7d608/664f91f95e897f99aa646fd7_icon-support.svg: ![\\n⟨30⟩ https://cdn.prod.website-files.com/63dd790039a2b29044f7d608/657cdff9dd1607d8158c4ff1_resources-about.svg: ![\\n⟨31⟩ https://cdn.prod.website-files.com/63dd790039a2b29044f7d608/657cdff8e0747baa9bf63b93_resources-careers.svg: ![\\n⟨32⟩ https://cdn.prod.website-files.com/63dd790039a2b29044f7d608/65dcf0b83dac61f48eeb7584_for-partners-nav-icon.svg: ![\\n⟨33⟩ https://cdn.prod.website-files.com/63dd790039a2b29044f7d608/657cdff83970773550b88b4d_resources-security.svg: ![\\n⟨34⟩ https://cdn.prod.website-files.com/63dd790039a2b29044f7d608/657cdff867546782a3db2846_resources-privacy.svg: ![\\n⟨35⟩ https://cdn.prod.website-files.com/63dd790039a2b29044f7d608/657cdff814d9bd3327b13952_resources-blog.svg: ![\\n⟨36⟩ https://cdn.prod.website-files.com/63dd790039a2b29044f7d608/657cdffa3e44cc316890cbe4_resources-whitepapers.svg: ![\\n⟨37⟩ https://cdn.prod.website-files.com/63dd790039a2b29044f7d608/664f92611bbc9020ad5e002d_icon-customer-stories.svg: ![\\n⟨38⟩ https://cdn.prod.website-files.com/63deb4700c95fc8b0d114fde/6751d9c7cb9992623918650d_Blog%2C%20Documents%20Beta%20v2.png: ![\\n⟨39⟩ https://cdn.prod.website-files.com/63deb4700c95fc8b0d114fde/6733e00076f9b18e5e18be78_Cover%20\\\\(1\\\\: ![\\n⟨40⟩ https://tryfinch.com/</pricing>: Pricing\\n⟨41⟩ https://tryfinch.com/<https:/dashboard.tryfinch.com/login>: Sign In\\n⟨42⟩ https://tryfinch.com/<https:/dashboard.tryfinch.com/signup>: Sign Up\\n⟨43⟩ https://tryfinch.com/</sales>: Talk to Sales\\n⟨44⟩ https://cdn.prod.website-files.com/63dd790039a2b29044f7d608/63e063443700f08aebd8c221_black-arrow.svg: Sign Up![\\n⟨45⟩ https://cdn.prod.website-files.com/63dd790039a2b29044f7d608/657cb810b376a8df459ab4ef_nav-deductions.svg: ![\\n⟨46⟩ https://cdn.prod.website-files.com/63dd790039a2b29044f7d608/63e0201368f8e94d41786a12_trainual.svg: Trainual\\n⟨47⟩ https://cdn.prod.website-files.com/63dd790039a2b29044f7d608/65a1d0628fb71aacd6614481_solution-401k-retirement.svg: ![\\n⟨48⟩ https://cdn.prod.website-files.com/63dd790039a2b29044f7d608/63e546d7c8989b2c7f7f0423_Frame.svg: Human Interest\\n⟨49⟩ https://cdn.prod.website-files.com/63dd790039a2b29044f7d608/65a1d0624621b6acf81a188e_solutions-employee-benefits.svg: ![\\n⟨50⟩ https://cdn.prod.website-files.com/63dd790039a2b29044f7d608/65a1d18873331a788fc5f34f_tempopay.svg: TempoPay\\n⟨51⟩ https://cdn.prod.website-files.com/63dd790039a2b29044f7d608/657cb81217e73f3ab2e38c95_nav-payroll.svg: ![\\n⟨52⟩ https://cdn.prod.website-files.com/63dd790039a2b29044f7d608/64dd6c709b0c6c5764667c2e_logo-carta.png: Carta\\n⟨53⟩ https://cdn.prod.website-files.com/63dd790039a2b29044f7d608/65a1d0628fb71aacd661448d_solutions-tax-compliance.svg: ![\\n⟨54⟩ https://cdn.prod.website-files.com/63dd790039a2b29044f7d608/65a1d188f5eef2ee37c95a90_secureframe%20logo.svg: SecureFrame\\n⟨55⟩ https://cdn.prod.website-files.com/63dd790039a2b29044f7d608/65a1d0627c2bc43447bdaea8_solutions-insurance.svg: ![\\n⟨56⟩ https://cdn.prod.website-files.com/63dd790039a2b29044f7d608/65a1d18889f7470b14fcf546_insurepay%20logo.svg: InsurePay\\n⟨57⟩ https://tryfinch.com/<#>: Prioritize privacyFinch discloses data privacy practices right from the start, so end users know where and how their data is transferred.\\n⟨58⟩ https://tryfinch.com/<#w-tabs-0-data-w-pane-0>: HRIS\\n⟨59⟩ https://tryfinch.com/<https:/developer.tryfinch.com/docs/reference/b3A6MTcxMzYwODg-company>: Read the company API\\n⟨60⟩ https://tryfinch.com/<https:/developer.tryfinch.com/docs/reference/b3A6MTcxMzYwODk-directory>: Read the directory API\\n⟨61⟩ https://tryfinch.com/<https:/developer.tryfinch.com/docs/reference/b3A6MTcxMzYwOTA-individual>: Read the individual API\\n⟨62⟩ https://tryfinch.com/<https:/developer.tryfinch.com/docs/reference/b3A6MTcxMzYwOTE-employment>: Read the employment API\\n⟨63⟩ https://tryfinch.com/<https:/developer.tryfinch.com/docs/reference/b3A6MTcxMzYwOTI-payment>: Read the payment API\\n⟨64⟩ https://tryfinch.com/<https:/developer.tryfinch.com/docs/reference/b3A6MTcxMzYwOTM-pay-statement>: Read the pay statement API\\n⟨65⟩ https://tryfinch.com/<https:/developer.tryfinch.com/docs/reference/d22e2304e8c9c-get-all-benefits>: Read the benefits API\\n⟨66⟩ https://tryfinch.com/</authors/kiera-blessing>: View author\\n⟨67⟩ https://tryfinch.com/</blog/ubiquity-saves-80-hours-per-week-with-automation>: View blog post\\n⟨68⟩ https://tryfinch.com/</blog/candoriq-saves-500k-year-and-accelerates-innovation-with-finch>: View blog post\\n⟨69⟩ https://tryfinch.com/</blog/awardco-and-ukg-launch-partnership-10-months-faster-with-finch>: View blog post\\n⟨70⟩ https://tryfinch.com/</product/organization>: Organization\\n⟨71⟩ https://tryfinch.com/</product/payroll>: Payroll\\n⟨72⟩ https://tryfinch.com/</product/deductions>: Deductions\\n⟨73⟩ https://tryfinch.com/</solutions/401k-retirement>: 401k and Retirement\\n⟨74⟩ https://tryfinch.com/</solutions/employee-benefits>: Employee Benefits\\n⟨75⟩ https://tryfinch.com/</solutions/hr-technology>: HR Technology\\n⟨76⟩ https://tryfinch.com/</solutions/b2b-fintech>: B2B Fintech\\n⟨77⟩ https://tryfinch.com/</solutions/tax-compliance>: Tax & Compliance\\n⟨78⟩ https://tryfinch.com/</solutions/insurance>: Insurance\\n⟨79⟩ https://tryfinch.com/<https:/www.tryfinch.com/integrations/quickbooks-online-payroll>: Intuit Quickbooks\\n⟨80⟩ https://tryfinch.com/<https:/www.tryfinch.com/integrations/gusto>: Gusto\\n⟨81⟩ https://tryfinch.com/<https:/www.tryfinch.com/integrations/adp-run>: Run Powered by ADP\\n⟨82⟩ https://tryfinch.com/<https:/www.tryfinch.com/integrations/paychex>: Paychex Flex\\n⟨83⟩ https://tryfinch.com/<https:/developer.tryfinch.com/>: Documentation\\n⟨84⟩ https://tryfinch.com/</finch-api>: Finch API\\n⟨85⟩ https://tryfinch.com/<https:/status.tryfinch.com/>: API Status\\n⟨86⟩ https://tryfinch.com/<https:/changelog.tryfinch.com/>: Changelog\\n⟨87⟩ https://tryfinch.com/</blog>: Blog\\n⟨88⟩ https://tryfinch.com/</tag/case-study>: Customer Stories\\n⟨89⟩ https://tryfinch.com/</whitepapers>: Whitepapers\\n⟨90⟩ https://tryfinch.com/</company/about>: About Us\\n⟨91⟩ https://tryfinch.com/</careers>: Careers\\n⟨92⟩ https://tryfinch.com/</for-employers>: For Employers\\n⟨93⟩ https://tryfinch.com/</for-partners>: For Partners\\n⟨94⟩ https://cdn.prod.website-files.com/63dd790039a2b29044f7d608/63dd9929c48a7e4bb078baef_linkedin.svg: ![\\n⟨95⟩ https://tryfinch.com/</legal/privacy>: Privacy Policy\\n⟨96⟩ https://tryfinch.com/</legal/terms>: Terms\\n⟨97⟩ https://tryfinch.com/</company/security>: Security\\n' fit_markdown='' fit_html=''",
  "generated_description": "Finch, launched in 2020 and part of Y Combinator's Summer 2020 batch, positions itself as a game-changer in the fintech and HR-tech sectors. Based in San Francisco, Finch is on a mission to serve as the universal API for payroll and HR. Their innovative API helps organizations securely and compliantly integrate employee data and financial information across various applications—a transparency win in a traditionally opaque domain.\n\nThe Finch API allows developers and administrators to tap into previously closed payroll systems, unlocking crucial data that drives multiple use cases in lending, insurance, employee benefits, financial planning, and HR management. With a growing team of 63 employees, Finch aims to streamline and modernize employment infrastructure for businesses, paving the way for easier onboarding, efficient payroll management, and seamless integration across different systems. \n\nWhat’s impressive about Finch is their commitment to providing an all-in-one solution for organizations' HR and payroll needs. Developers love their platform for several reasons:\n\n1. **Unified Data Model**: Finch provides market-leading compatibility with various HRIS and payroll systems. As new systems are added, users can activate them with just one click, making it a breeze for developers to expand integration capabilities.\n\n2. **Enterprise-Grade Security**: They take data security seriously, employing advanced encryption protocols that protect user data at every stage.\n\n3. **Developer Experience**: Finch focuses on a positive developer experience with efficient tools like sandboxes and SDKs, allowing users to build and maintain integrations without frictions.\n\nTheir suite of products includes APIs that cater to organization and employee data, payroll, deductions, and more. Finch also supports critical solutions like 401k and retirement plans, employee benefits, tax compliance, and insurance—all tailored to enhance operational efficiency and employee experience.\n\nCustomer success stories are pivotal for Finch, with companies like Ubiquity and CandorIQ reporting significant time savings and cost reduction through Finch’s automated processes.\n\nIf you’re looking to modernize your HR and payroll systems or tap into powerful integrations that simplify complex data flows, Finch is worth a closer look. For more information or to explore their API, visit [Finch's website](https://tryfinch.com)."
}