{
  "links": "https://www.ycombinator.com/companies/universe",
  "name": "Universe",
  "headline": "Design and build any kind of website. On your iPhone or iPad.",
  "batch": "W18",
  "description": "Our mission is to empower everyone to build the internet. Universe is a magical new way to build websites –– it’s the first website builder designed for phones. Our app makes it easy for anyone to make a great looking website and start selling online in minutes from your iPhone, iPad, and Mac. And we make it as fun as playing with Legos! \r\n\nGive it a try: https://apps.apple.com/us/app/id1211437633\r\n\nExplore sites made on Universe: https://onuniverse.com/explore\r\n\nWe are a remote-first 20+ person company with people all over the US. We were YC W18 and have raised $17.2MM in funding from Google Ventures, General Catalyst, Javelin Venture Partners, Box Group, and more top investors.\r\n\nWe value individual agency and ownership –– which guides our product design and our company’s culture. While other companies offer lots of perks, we prioritize your freedom: work from anywhere, in the way you’re at your best. We believe that an individual’s capacity for growth is far larger than most understand, and we’ve designed an environment to support rapid, continuous learning. Ideas here come from everyone, initiative is respected, and quality matters. We are here to build something special and enduring.",
  "activity_status": "Active",
  "website": "http://onuniverse.com",
  "founded_date": 2015.0,
  "team_size": 25.0,
  "location": "New York",
  "group_partner": null,
  "group_partner_yc": null,
  "company_linkedin": null,
  "company_twitter": null,
  "tags": "industry:design-tools; location:new-york",
  "founders": [
    {
      "name": "Joseph Cohen, Founder/CEO",
      "description": "Founder of Univer.se and Infinite Machine",
      "linkedin": "https://www.linkedin.com/in/josephmcohen/"
    }
  ],
  "status": true,
  "markdown": "raw_markdown=\"  * [Home](http://onuniverse.com/</>)\\n  * [Learn To Build On Universe](http://onuniverse.com/</learn>)\\n  * [Pricing And Plans](http://onuniverse.com/</pricing>)\\n  * [Sites Made On Universe](http://onuniverse.com/</explore>)\\n  * [How To Build A Link In Bio Website For Free](http://onuniverse.com/</link-in-bio>)\\n  * [Guides](http://onuniverse.com/</guides>)\\n  * [Creator Interviews](http://onuniverse.com/</creators>)\\n  * [Jobs](http://onuniverse.com/</jobs>)\\n  * [Contact Us](http://onuniverse.com/</connect-with-us>)\\n  * [Legal](http://onuniverse.com/</legal>)\\n  * [Fee Structures](http://onuniverse.com/</fee-structures>)\\n\\n\\n[GET STARTED](http://onuniverse.com/<https:/web.univer.se/>)\\n![](http://onuniverse.com/_assets/F813202C-E572-496E-8145-827F79A57103?q=65&auto=compress,format&w=200&fit=crop)\\n## Universe is a visual, no-code website builder that you can use from any device. Drag and drop blocks to construct your pages on your phone, tablet, or computer. Building websites should be fun, fast, and easy. Get started for free.\\nCreate an online store, portfolio, event page, blog, fan site, or anything else you can imagine. There are hundreds of professionally designed templates to choose from, or you can start from scratch. \\n2023 Apple Design Award winner. \\nOver 7K 5-star reviews.\\nOver one million sites built. \\n[\\uf8ff Download on the App Store](http://onuniverse.com/<https:/apps.apple.com/us/app/universe-website-builder/id1211437633>)\\n[🌐 Try out the Web App](http://onuniverse.com/<https:/web.univer.se/>)\\n## Use AI to generate website elements in minutes, build on top of designer templates, or start from scratch.\\n![](http://onuniverse.com/_assets/D5DF5FD1-DE9B-4241-BFF8-05B23FE799C9?q=65&auto=compress,format&w=200&fit=clip)\\nBuild your site visually with our drag and drop editor. No HTML, no CSS. Just arrange your content on the Grid. \\n## Sell anything, from physical goods to digital downloads.\\n![](http://onuniverse.com/_assets/35325B2F-0C33-4A81-B41C-7EF3F3979326?q=65&auto=compress,format&w=200&fit=clip)\\nAdd a sell block and you're open for business. Plus, perks like discounted shipping labels to help your business from start to finish.\\n## Build your way, no code required.\\n![](http://onuniverse.com/_assets/2FB3C3CD-E97C-47E8-A3F2-AF6B76A605DD?q=65&auto=compress,format&w=200&fit=clip)\\nDrag, drop and rearrange elements to build your site. See exactly what your site will look like as you're making it with our visual editor. All without having to touch any code.\\n## Grow your audience with built-in analytics and powerful integrations.\\n![](http://onuniverse.com/_assets/3966FDD9-57C7-44CF-88BC-C7E3825B3362?q=65&auto=compress,format&w=200&fit=clip)\\nTrack site traffic, grow your mailing list, and run ads on popular social media networks.\\n## Pricing\\n### We have four plans: Free, Base, Pro, and Complete. Below, you can find a rough outline of what each plan includes. \\n![](http://onuniverse.com/_assets/DC4F0FA1-BB82-4715-8C9D-C8A644264EE2?q=65&auto=compress,format&w=200&fit=clip)\\nEverything you need to build your brand and sell it online.\\n![](http://onuniverse.com/_assets/4134C554-240D-4945-9779-37CCF9D57335?q=65&auto=compress,format&w=200&fit=clip)\\n![](http://onuniverse.com/_assets/90D23D1D-2E8B-418F-A7CB-8A65163A0751?q=65&auto=compress,format&w=200&fit=clip)\\n![](http://onuniverse.com/_assets/1DA4A8A5-2E19-4D04-A8AC-0F32C38C107C?q=65&auto=compress,format&w=200&fit=clip)\\nPRO MAIL TOOLS\\nCOMMERCE\\nADVANCED BRAND TOOLS\\n$25/month\\nor $200/year\\n[Learn more →](http://onuniverse.com/<https:/univer.se/pricing>)\\n![](http://onuniverse.com/_assets/63BD5FD4-032B-477D-88BE-CD2D7262C2E5?q=65&auto=compress,format&w=200&fit=clip)\\nLaunch an online store and get your business started.\\n![](http://onuniverse.com/_assets/4134C554-240D-4945-9779-37CCF9D57335?q=65&auto=compress,format&w=200&fit=clip)\\n![](http://onuniverse.com/_assets/90D23D1D-2E8B-418F-A7CB-8A65163A0751?q=65&auto=compress,format&w=200&fit=clip)\\n![](http://onuniverse.com/_assets/1DA4A8A5-2E19-4D04-A8AC-0F32C38C107C?q=65&auto=compress,format&w=200&fit=clip)\\nPRO MAIL TOOLS\\nCOMMERCE\\nBRAND TOOLS\\n$12/month\\nor $72/year\\n[Learn more →](http://onuniverse.com/<https:/univer.se/pricing>)\\n![](http://onuniverse.com/_assets/8F97D670-212D-4FE6-9679-F01965CF7CEE?q=65&auto=compress,format&w=200&fit=clip)\\nCreate without limits with best-in-class tools, support, and commerce functionality.\\n![](http://onuniverse.com/_assets/4134C554-240D-4945-9779-37CCF9D57335?q=65&auto=compress,format&w=200&fit=clip)\\n![](http://onuniverse.com/_assets/90D23D1D-2E8B-418F-A7CB-8A65163A0751?q=65&auto=compress,format&w=200&fit=clip)\\n![](http://onuniverse.com/_assets/5B76F265-E498-4C57-BD34-112F2F3EE9A2?q=65&auto=compress,format&w=200&fit=clip)\\nPRO MAIL TOOLS\\nCOMMERCE\\n4K UPLOADS\\n$50/month\\nor $500/year\\n[Learn more →](http://onuniverse.com/<https:/univer.se/pricing>)\\n![](http://onuniverse.com/_assets/1259F451-3931-44DC-ABD8-97A86C9013E2?q=65&auto=compress,format&w=200&fit=clip)\\nCreate a unique new website, portfolio, or link in bio. \\n![](http://onuniverse.com/_assets/4134C554-240D-4945-9779-37CCF9D57335?q=65&auto=compress,format&w=200&fit=clip)\\n![](http://onuniverse.com/_assets/05F779E6-BFAE-4A20-9CCC-DEFA5AD9C3B9?q=65&auto=compress,format&w=200&fit=clip)\\n![](http://onuniverse.com/_assets/3055F7FD-91AB-49D7-B464-6911BE4066FE?q=65&auto=compress,format&w=200&fit=clip)\\nMAILING LIST\\nUNLIMITED BLOCKS\\nSEO TOOLS\\n$0.00\\n[Learn more →](http://onuniverse.com/<https:/univer.se/pricing>)\\n[\\uf8ff Download on the App Store](http://onuniverse.com/<https:/apps.apple.com/us/app/universe-website-builder/id1211437633>)\\n[🌐 Try out the Web App](http://onuniverse.com/<https:/web.univer.se/>)\\n## Site Gallery\\n### We’re proud to build a product where people can build creative, weird, wild (or none of those things) websites. Check out a sampling of Universe sites below. \\n![](http://onuniverse.com/_assets/9ec2c165-db48-4dc2-8353-81b77a29bd4c?q=65&auto=compress,format&w=200&fit=crop)\\n![](http://onuniverse.com/_assets/EAB4F371-0548-4960-8BA4-8BA3E5233B5E?q=65&w=200&auto=compress,format)\\n![](http://onuniverse.com/_assets/70679F52-F512-4C25-8A59-A39BAD918434?q=65&w=200&auto=compress,format)\\n![](http://onuniverse.com/_assets/F8EC6698-6DF2-4487-BAEE-11656B104F0E?q=65&w=200&auto=compress,format)\\n![](http://onuniverse.com/_assets/0beeb223-f540-498d-af2f-b966317c8173?q=65&w=200&auto=compress,format)\\n![](http://onuniverse.com/_assets/d6f41e0a-cace-4c1f-bf54-222d3d05ee45?q=65&w=200&auto=compress,format)\\n![](http://onuniverse.com/_assets/ab07e202-96bf-4d9b-8991-9632598b7690?q=65&w=200&auto=compress,format)\\n![](http://onuniverse.com/_assets/c80c3fc7-11ef-4a51-87df-fbd4ced7e6c8?q=65&w=200&auto=compress,format)\\n![](http://onuniverse.com/_assets/1b12d0ba-0f7c-4c42-8663-969b39776c4c?q=65&w=200&auto=compress,format)\\nTap + swipe\\nto build your site\\nDrag + drop\\nopen up shop\\nFeatures\\n[Custom website domain](http://onuniverse.com/<https:/help.univer.se/hc/en-us/sections/360013578131-Domains>)\\n[Link in bio site](http://onuniverse.com/<https:/www.univer.se/link-in-bio>)[E-commerce](http://onuniverse.com/<https:/help.univer.se/hc/en-us/categories/360004568751-Commerce-at-Univer-se>)[Email Management](http://onuniverse.com/<https:/help.univer.se/hc/en-us/sections/360010918032-Email>)[Website Templates](http://onuniverse.com/<https:/web.univer.se/>)[SEO](http://onuniverse.com/<https:/help.univer.se/hc/en-us/sections/27043260282388-SEO>)\\nIntegrations\\n[PayPal](http://onuniverse.com/<https:/help.univer.se/hc/en-us/sections/13454266241172-PayPal-Block>)\\n[Cash](http://onuniverse.com/<https:/help.univer.se/hc/en-us/articles/360049757652-How-To-Accept-Payments-with-PayPal-or-Cash-App-Using-the-Cash-Block>)[YouTube](http://onuniverse.com/<https:/help.univer.se/hc/en-us/articles/360049757732-Univer-se-Basics-Youtube-Block>)[Vimeo](http://onuniverse.com/<https:/help.univer.se/hc/en-us/articles/27045865241364-Univer-se-Basics-Vimeo-Block>)[Soundcloud](http://onuniverse.com/<https:/help.univer.se/hc/en-us/articles/360050212411-Univer-se-Basics-SoundCloud-Block>)[GIPHY](http://onuniverse.com/<https:/help.univer.se/hc/en-us/articles/360050212391-Univer-se-Basics-Giphy-Block>)[Maps](http://onuniverse.com/<https:/help.univer.se/hc/en-us/articles/360049757812-NEEDS-UPDATES-IMAGES-Universe-Basics-Map-Block>)\\nExplore\\n[Sites Built on Universe (all](http://onuniverse.com/<https:/univer.se/explore>))\\n[E-commerce Sites](http://onuniverse.com/<https:/explore.univer.se/commerce>)[Creator Interviews](http://onuniverse.com/<https:/univer.se/creators>)\\nUniverse\\n[Instagram](http://onuniverse.com/<https:/www.instagram.com/univer.se/>)\\n[YouTube](http://onuniverse.com/<https:/www.youtube.com/c/Universeapp>)[Contact](http://onuniverse.com/<https:/www.univer.se/connect-with-us>)[Jobs](http://onuniverse.com/<https:/www.univer.se/jobs>)[Legal](http://onuniverse.com/<https:/www.univer.se/legal>)\\nE-commerce\\n[Sell on Universe](http://onuniverse.com/<https:/help.univer.se/hc/en-us/categories/360004568751-Commerce-at-Univer-se>)\\n[E-commerce Templates](http://onuniverse.com/<https:/web.univer.se/>)[Commerce FAQs](http://onuniverse.com/<https:/help.univer.se/hc/en-us/categories/360004568751-Commerce-at-Univer-se>)\\nStart\\n[Login](http://onuniverse.com/<https:/web.univer.se/sign-in>)\\n[Create an Account](http://onuniverse.com/<https:/web.univer.se/sign-up>)\\nResources\\n[Help Center](http://onuniverse.com/<https:/help.univer.se/hc/en-us>)\\n[Community](http://onuniverse.com/<https:/community.univer.se/>)[Universe 101](http://onuniverse.com/<https:/univer.se/guides>)\\nPricing + Plans\\n[Compare Plans](http://onuniverse.com/<https:/univer.se/pricing/compare-plans>)\\nWebsites for humans. \\n\" markdown_with_citations=\"  * Home⟨1⟩\\n  * Learn To Build On Universe⟨2⟩\\n  * Pricing And Plans⟨3⟩\\n  * Sites Made On Universe⟨4⟩\\n  * How To Build A Link In Bio Website For Free⟨5⟩\\n  * Guides⟨6⟩\\n  * Creator Interviews⟨7⟩\\n  * Jobs⟨8⟩\\n  * Contact Us⟨9⟩\\n  * Legal⟨10⟩\\n  * Fee Structures⟨11⟩\\n\\n\\nGET STARTED⟨12⟩\\n![](http://onuniverse.com/_assets/F813202C-E572-496E-8145-827F79A57103?q=65&auto=compress,format&w=200&fit=crop)\\n## Universe is a visual, no-code website builder that you can use from any device. Drag and drop blocks to construct your pages on your phone, tablet, or computer. Building websites should be fun, fast, and easy. Get started for free.\\nCreate an online store, portfolio, event page, blog, fan site, or anything else you can imagine. There are hundreds of professionally designed templates to choose from, or you can start from scratch. \\n2023 Apple Design Award winner. \\nOver 7K 5-star reviews.\\nOver one million sites built. \\n\\uf8ff Download on the App Store⟨13⟩\\n🌐 Try out the Web App⟨12⟩\\n## Use AI to generate website elements in minutes, build on top of designer templates, or start from scratch.\\n![](http://onuniverse.com/_assets/D5DF5FD1-DE9B-4241-BFF8-05B23FE799C9?q=65&auto=compress,format&w=200&fit=clip)\\nBuild your site visually with our drag and drop editor. No HTML, no CSS. Just arrange your content on the Grid. \\n## Sell anything, from physical goods to digital downloads.\\n![](http://onuniverse.com/_assets/35325B2F-0C33-4A81-B41C-7EF3F3979326?q=65&auto=compress,format&w=200&fit=clip)\\nAdd a sell block and you're open for business. Plus, perks like discounted shipping labels to help your business from start to finish.\\n## Build your way, no code required.\\n![](http://onuniverse.com/_assets/2FB3C3CD-E97C-47E8-A3F2-AF6B76A605DD?q=65&auto=compress,format&w=200&fit=clip)\\nDrag, drop and rearrange elements to build your site. See exactly what your site will look like as you're making it with our visual editor. All without having to touch any code.\\n## Grow your audience with built-in analytics and powerful integrations.\\n![](http://onuniverse.com/_assets/3966FDD9-57C7-44CF-88BC-C7E3825B3362?q=65&auto=compress,format&w=200&fit=clip)\\nTrack site traffic, grow your mailing list, and run ads on popular social media networks.\\n## Pricing\\n### We have four plans: Free, Base, Pro, and Complete. Below, you can find a rough outline of what each plan includes. \\n![](http://onuniverse.com/_assets/DC4F0FA1-BB82-4715-8C9D-C8A644264EE2?q=65&auto=compress,format&w=200&fit=clip)\\nEverything you need to build your brand and sell it online.\\n![](http://onuniverse.com/_assets/4134C554-240D-4945-9779-37CCF9D57335?q=65&auto=compress,format&w=200&fit=clip)\\n![](http://onuniverse.com/_assets/90D23D1D-2E8B-418F-A7CB-8A65163A0751?q=65&auto=compress,format&w=200&fit=clip)\\n![](http://onuniverse.com/_assets/1DA4A8A5-2E19-4D04-A8AC-0F32C38C107C?q=65&auto=compress,format&w=200&fit=clip)\\nPRO MAIL TOOLS\\nCOMMERCE\\nADVANCED BRAND TOOLS\\n$25/month\\nor $200/year\\nLearn more →⟨14⟩\\n![](http://onuniverse.com/_assets/63BD5FD4-032B-477D-88BE-CD2D7262C2E5?q=65&auto=compress,format&w=200&fit=clip)\\nLaunch an online store and get your business started.\\n![](http://onuniverse.com/_assets/4134C554-240D-4945-9779-37CCF9D57335?q=65&auto=compress,format&w=200&fit=clip)\\n![](http://onuniverse.com/_assets/90D23D1D-2E8B-418F-A7CB-8A65163A0751?q=65&auto=compress,format&w=200&fit=clip)\\n![](http://onuniverse.com/_assets/1DA4A8A5-2E19-4D04-A8AC-0F32C38C107C?q=65&auto=compress,format&w=200&fit=clip)\\nPRO MAIL TOOLS\\nCOMMERCE\\nBRAND TOOLS\\n$12/month\\nor $72/year\\nLearn more →⟨14⟩\\n![](http://onuniverse.com/_assets/8F97D670-212D-4FE6-9679-F01965CF7CEE?q=65&auto=compress,format&w=200&fit=clip)\\nCreate without limits with best-in-class tools, support, and commerce functionality.\\n![](http://onuniverse.com/_assets/4134C554-240D-4945-9779-37CCF9D57335?q=65&auto=compress,format&w=200&fit=clip)\\n![](http://onuniverse.com/_assets/90D23D1D-2E8B-418F-A7CB-8A65163A0751?q=65&auto=compress,format&w=200&fit=clip)\\n![](http://onuniverse.com/_assets/5B76F265-E498-4C57-BD34-112F2F3EE9A2?q=65&auto=compress,format&w=200&fit=clip)\\nPRO MAIL TOOLS\\nCOMMERCE\\n4K UPLOADS\\n$50/month\\nor $500/year\\nLearn more →⟨14⟩\\n![](http://onuniverse.com/_assets/1259F451-3931-44DC-ABD8-97A86C9013E2?q=65&auto=compress,format&w=200&fit=clip)\\nCreate a unique new website, portfolio, or link in bio. \\n![](http://onuniverse.com/_assets/4134C554-240D-4945-9779-37CCF9D57335?q=65&auto=compress,format&w=200&fit=clip)\\n![](http://onuniverse.com/_assets/05F779E6-BFAE-4A20-9CCC-DEFA5AD9C3B9?q=65&auto=compress,format&w=200&fit=clip)\\n![](http://onuniverse.com/_assets/3055F7FD-91AB-49D7-B464-6911BE4066FE?q=65&auto=compress,format&w=200&fit=clip)\\nMAILING LIST\\nUNLIMITED BLOCKS\\nSEO TOOLS\\n$0.00\\nLearn more →⟨14⟩\\n\\uf8ff Download on the App Store⟨13⟩\\n🌐 Try out the Web App⟨12⟩\\n## Site Gallery\\n### We’re proud to build a product where people can build creative, weird, wild (or none of those things) websites. Check out a sampling of Universe sites below. \\n![](http://onuniverse.com/_assets/9ec2c165-db48-4dc2-8353-81b77a29bd4c?q=65&auto=compress,format&w=200&fit=crop)\\n![](http://onuniverse.com/_assets/EAB4F371-0548-4960-8BA4-8BA3E5233B5E?q=65&w=200&auto=compress,format)\\n![](http://onuniverse.com/_assets/70679F52-F512-4C25-8A59-A39BAD918434?q=65&w=200&auto=compress,format)\\n![](http://onuniverse.com/_assets/F8EC6698-6DF2-4487-BAEE-11656B104F0E?q=65&w=200&auto=compress,format)\\n![](http://onuniverse.com/_assets/0beeb223-f540-498d-af2f-b966317c8173?q=65&w=200&auto=compress,format)\\n![](http://onuniverse.com/_assets/d6f41e0a-cace-4c1f-bf54-222d3d05ee45?q=65&w=200&auto=compress,format)\\n![](http://onuniverse.com/_assets/ab07e202-96bf-4d9b-8991-9632598b7690?q=65&w=200&auto=compress,format)\\n![](http://onuniverse.com/_assets/c80c3fc7-11ef-4a51-87df-fbd4ced7e6c8?q=65&w=200&auto=compress,format)\\n![](http://onuniverse.com/_assets/1b12d0ba-0f7c-4c42-8663-969b39776c4c?q=65&w=200&auto=compress,format)\\nTap + swipe\\nto build your site\\nDrag + drop\\nopen up shop\\nFeatures\\nCustom website domain⟨15⟩\\nLink in bio site⟨16⟩E-commerce⟨17⟩Email Management⟨18⟩Website Templates⟨12⟩SEO⟨19⟩\\nIntegrations\\nPayPal⟨20⟩\\nCash⟨21⟩YouTube⟨22⟩Vimeo⟨23⟩Soundcloud⟨24⟩GIPHY⟨25⟩Maps⟨26⟩\\nExplore\\nSites Built on Universe (all⟨27⟩)\\nE-commerce Sites⟨28⟩Creator Interviews⟨29⟩\\nUniverse\\nInstagram⟨30⟩\\nYouTube⟨31⟩Contact⟨32⟩Jobs⟨33⟩Legal⟨34⟩\\nE-commerce\\nSell on Universe⟨17⟩\\nE-commerce Templates⟨12⟩Commerce FAQs⟨17⟩\\nStart\\nLogin⟨35⟩\\nCreate an Account⟨36⟩\\nResources\\nHelp Center⟨37⟩\\nCommunity⟨38⟩Universe 101⟨39⟩\\nPricing + Plans\\nCompare Plans⟨40⟩\\nWebsites for humans. \\n\" references_markdown='\\n\\n## References\\n\\n⟨1⟩ http://onuniverse.com/</>: Home\\n⟨2⟩ http://onuniverse.com/</learn>: Learn To Build On Universe\\n⟨3⟩ http://onuniverse.com/</pricing>: Pricing And Plans\\n⟨4⟩ http://onuniverse.com/</explore>: Sites Made On Universe\\n⟨5⟩ http://onuniverse.com/</link-in-bio>: How To Build A Link In Bio Website For Free\\n⟨6⟩ http://onuniverse.com/</guides>: Guides\\n⟨7⟩ http://onuniverse.com/</creators>: Creator Interviews\\n⟨8⟩ http://onuniverse.com/</jobs>: Jobs\\n⟨9⟩ http://onuniverse.com/</connect-with-us>: Contact Us\\n⟨10⟩ http://onuniverse.com/</legal>: Legal\\n⟨11⟩ http://onuniverse.com/</fee-structures>: Fee Structures\\n⟨12⟩ http://onuniverse.com/<https:/web.univer.se/>: GET STARTED\\n⟨13⟩ http://onuniverse.com/<https:/apps.apple.com/us/app/universe-website-builder/id1211437633>: \\uf8ff Download on the App Store\\n⟨14⟩ http://onuniverse.com/<https:/univer.se/pricing>: Learn more →\\n⟨15⟩ http://onuniverse.com/<https:/help.univer.se/hc/en-us/sections/360013578131-Domains>: Custom website domain\\n⟨16⟩ http://onuniverse.com/<https:/www.univer.se/link-in-bio>: Link in bio site\\n⟨17⟩ http://onuniverse.com/<https:/help.univer.se/hc/en-us/categories/360004568751-Commerce-at-Univer-se>: E-commerce\\n⟨18⟩ http://onuniverse.com/<https:/help.univer.se/hc/en-us/sections/360010918032-Email>: Email Management\\n⟨19⟩ http://onuniverse.com/<https:/help.univer.se/hc/en-us/sections/27043260282388-SEO>: SEO\\n⟨20⟩ http://onuniverse.com/<https:/help.univer.se/hc/en-us/sections/13454266241172-PayPal-Block>: PayPal\\n⟨21⟩ http://onuniverse.com/<https:/help.univer.se/hc/en-us/articles/360049757652-How-To-Accept-Payments-with-PayPal-or-Cash-App-Using-the-Cash-Block>: Cash\\n⟨22⟩ http://onuniverse.com/<https:/help.univer.se/hc/en-us/articles/360049757732-Univer-se-Basics-Youtube-Block>: YouTube\\n⟨23⟩ http://onuniverse.com/<https:/help.univer.se/hc/en-us/articles/27045865241364-Univer-se-Basics-Vimeo-Block>: Vimeo\\n⟨24⟩ http://onuniverse.com/<https:/help.univer.se/hc/en-us/articles/360050212411-Univer-se-Basics-SoundCloud-Block>: Soundcloud\\n⟨25⟩ http://onuniverse.com/<https:/help.univer.se/hc/en-us/articles/360050212391-Univer-se-Basics-Giphy-Block>: GIPHY\\n⟨26⟩ http://onuniverse.com/<https:/help.univer.se/hc/en-us/articles/360049757812-NEEDS-UPDATES-IMAGES-Universe-Basics-Map-Block>: Maps\\n⟨27⟩ http://onuniverse.com/<https:/univer.se/explore>: Sites Built on Universe (all\\n⟨28⟩ http://onuniverse.com/<https:/explore.univer.se/commerce>: E-commerce Sites\\n⟨29⟩ http://onuniverse.com/<https:/univer.se/creators>: Creator Interviews\\n⟨30⟩ http://onuniverse.com/<https:/www.instagram.com/univer.se/>: Instagram\\n⟨31⟩ http://onuniverse.com/<https:/www.youtube.com/c/Universeapp>: YouTube\\n⟨32⟩ http://onuniverse.com/<https:/www.univer.se/connect-with-us>: Contact\\n⟨33⟩ http://onuniverse.com/<https:/www.univer.se/jobs>: Jobs\\n⟨34⟩ http://onuniverse.com/<https:/www.univer.se/legal>: Legal\\n⟨35⟩ http://onuniverse.com/<https:/web.univer.se/sign-in>: Login\\n⟨36⟩ http://onuniverse.com/<https:/web.univer.se/sign-up>: Create an Account\\n⟨37⟩ http://onuniverse.com/<https:/help.univer.se/hc/en-us>: Help Center\\n⟨38⟩ http://onuniverse.com/<https:/community.univer.se/>: Community\\n⟨39⟩ http://onuniverse.com/<https:/univer.se/guides>: Universe 101\\n⟨40⟩ http://onuniverse.com/<https:/univer.se/pricing/compare-plans>: Compare Plans\\n' fit_markdown='' fit_html=''",
  "generated_description": "**Company Overview: Universe**\n\n**What We Do**: Universe is a no-code website builder that lets anyone design and launch websites using just their iPhone or iPad. Think of it as building with Legos, but for the web. Whether you need an online store, a blog, a portfolio, or any type of webpage, you can create something beautiful in minutes—no coding skills required. The app is designed to be intuitive and versatile, allowing users to drag and drop elements as they build.\n\n**Mission**: Our mission is clear: empower everyone to build the internet. We believe that creating a website should be fun, fast, and accessible to all.\n\n**Background**:\n- **Founded**: 2015 as part of Y Combinator's Winter 2018 batch.\n- **Funding**: Universe has successfully raised $17.2 million from prominent investors, including Google Ventures and General Catalyst.\n- **Team**: We operate as a remote-first company, with a dynamic team of over 25 employees spread across the United States.\n\n**Culture and Values**: At Universe, we foster an environment of individual agency and ownership. We steer clear of typical corporate perks and instead offer the freedom to work from anywhere—because we believe that creativity flourishes when people feel empowered. Every team member’s ideas are valued here, and we focus on rapid learning and improvement to build something meaningful and lasting.\n\n**Recognitions**: Our dedication to quality and design has not gone unnoticed. Universe was recognized with the 2023 Apple Design Award, and our app boasts over 7,000 five-star reviews, highlighting the satisfaction of our users. More than one million websites have been built with Universe, showcasing its growing footprint in the digital landscape.\n\n**Key Features**:\n- **User-Friendly Editing**: With our drag-and-drop interface, users can see real-time changes while building their site, making it easy to visualize the end product.\n- **E-Commerce Capabilities**: Start selling products or digital downloads effortlessly with features like sell blocks and analytics to track performance.\n- **Flexible Plans**: Current offerings include Free, Base, Pro, and Complete plans, ensuring there’s an option for various budgets and needs.\n\n**Explore & Get Started**: If you're interested in building your own site or want to see what others have created, check out our platform at [onuniverse.com](http://onuniverse.com). For a firsthand experience, you can download our app from the [App Store](https://apps.apple.com/us/app/id1211437633).\n\n**Join Us**: We're always on the lookout for passionate individuals who want to contribute to this exciting journey. If you resonate with our mission and values, consider joining our team!\n\nIn short, Universe is not just about creating websites; it's about empowering people to express themselves and thrive in the online space. So why wait? Dive in and start building!"
}